{
  "name": "Avery",
  "totalCards": 3,
  "cards": [
    {
      "id": "swsh6-130",
      "name": "Avery",
      "set": "swsh6",
      "setName": "Chilling Reign",
      "number": "130",
      "rarity": "Uncommon",
      "image": "https://assets.tcgdex.net/en/swsh/swsh6/130",
      "types": null,
      "illustrator": "Ken Sugimori"
    },
    {
      "id": "swsh6-187",
      "name": "Avery",
      "set": "swsh6",
      "setName": "Chilling Reign",
      "number": "187",
      "rarity": "Ultra Rare",
      "image": "https://assets.tcgdex.net/en/swsh/swsh6/187",
      "types": null,
      "illustrator": "kirisAki"
    },
    {
      "id": "swsh6-211",
      "name": "Avery",
      "set": "swsh6",
      "setName": "Chilling Reign",
      "number": "211",
      "rarity": "Secret Rare",
      "image": "https://assets.tcgdex.net/en/swsh/swsh6/211",
      "types": null,
      "illustrator": "kirisAki"
    }
  ]
}