{
  "name": "Brigette",
  "totalCards": 2,
  "cards": [
    {
      "id": "xy8-134",
      "name": "Brigette",
      "set": "xy8",
      "setName": "BREAKthrough",
      "number": "134",
      "rarity": "Uncommon",
      "image": "https://assets.tcgdex.net/en/xy/xy8/134",
      "types": null,
      "illustrator": "Megumi Mizutani"
    },
    {
      "id": "xy8-161",
      "name": "Brigette",
      "set": "xy8",
      "setName": "BREAKthrough",
      "number": "161",
      "rarity": "Ultra Rare",
      "image": "https://assets.tcgdex.net/en/xy/xy8/161",
      "types": null,
      "illustrator": "Megumi Mizutani"
    }
  ]
}