{
  "name": "Drasna",
  "totalCards": 2,
  "cards": [
    {
      "id": "sv08-173",
      "name": "Drasna",
      "set": "sv08",
      "setName": "Surging Sparks",
      "number": "173",
      "rarity": "Common",
      "image": "https://assets.tcgdex.net/en/sv/sv08/173",
      "types": null,
      "illustrator": "Hideki Ishikawa"
    },
    {
      "id": "sv08-231",
      "name": "Drasna",
      "set": "sv08",
      "setName": "Surging Sparks",
      "number": "231",
      "rarity": "Ultra Rare",
      "image": "https://assets.tcgdex.net/en/sv/sv08/231",
      "types": null,
      "illustrator": "Hideki Ishikawa"
    }
  ]
}