{
  "name": "Scizor GX",
  "totalCards": 4,
  "cards": [
    {
      "id": "sm7-158",
      "name": "Scizor GX",
      "set": "sm7",
      "setName": "Celestial Storm",
      "number": "158",
      "rarity": "Ultra Rare",
      "image": "https://assets.tcgdex.net/en/sm/sm7/158",
      "types": [
        "Metal"
      ],
      "illustrator": "5ban Graphics"
    },
    {
      "id": "sm7-175",
      "name": "Scizor GX",
      "set": "sm7",
      "setName": "Celestial Storm",
      "number": "175",
      "rarity": "Secret Rare",
      "image": "https://assets.tcgdex.net/en/sm/sm7/175",
      "types": [
        "Metal"
      ],
      "illustrator": "5ban Graphics"
    },
    {
      "id": "sm7-90",
      "name": "Scizor GX",
      "set": "sm7",
      "setName": "Celestial Storm",
      "number": "90",
      "rarity": "Ultra Rare",
      "image": "https://assets.tcgdex.net/en/sm/sm7/90",
      "types": [
        "Metal"
      ],
      "illustrator": "5ban Graphics"
    },
    {
      "id": "sma-SV72",
      "name": "Scizor-GX",
      "set": "sma",
      "setName": "Hidden Fates Shiny Vault",
      "number": "SV72",
      "rarity": "Shiny rare",
      "image": "https://assets.tcgdex.net/en/sm/sma/SV72",
      "types": [
        "Metal"
      ],
      "illustrator": "5ban Graphics"
    }
  ]
}