{
  "name": "Baxcalibur",
  "totalCards": 6,
  "cards": [
    {
      "id": "B2a-036",
      "name": "Baxcalibur",
      "set": "B2a",
      "setName": "Paldean Wonders",
      "number": "036",
      "rarity": "Tres Diamantes",
      "image": null,
      "types": [
        "Agua"
      ],
      "illustrator": "Oswaldo KATO"
    },
    {
      "id": "B2a-130",
      "name": "Baxcalibur",
      "set": "B2a",
      "setName": "Paldean Wonders",
      "number": "130",
      "rarity": "Corona",
      "image": null,
      "types": [
        "Agua"
      ],
      "illustrator": "PLANETA Igarashi"
    },
    {
      "id": "sv02-060",
      "name": "Baxcalibur",
      "set": "sv02",
      "setName": "Evoluciones en Paldea",
      "number": "060",
      "rarity": "Rara",
      "image": "https://assets.tcgdex.net/es/sv/sv02/060",
      "types": [
        "Agua"
      ],
      "illustrator": "Shin Nagasawa"
    },
    {
      "id": "sv02-210",
      "name": "Baxcalibur",
      "set": "sv02",
      "setName": "Evoluciones en Paldea",
      "number": "210",
      "rarity": "Rara Ilustración",
      "image": "https://assets.tcgdex.net/es/sv/sv02/210",
      "types": [
        "Agua"
      ],
      "illustrator": "Tomokazu Komiya"
    },
    {
      "id": "sv04.5-130",
      "name": "Baxcalibur",
      "set": "sv04.5",
      "setName": "Destinos de Paldea",
      "number": "130",
      "rarity": "Shiny rare",
      "image": "https://assets.tcgdex.net/es/sv/sv04.5/130",
      "types": [
        "Agua"
      ],
      "illustrator": "GOSSAN"
    },
    {
      "id": "svp-019",
      "name": "Baxcalibur",
      "set": "svp",
      "setName": "SVP Black Star Promos",
      "number": "019",
      "rarity": "Ninguno",
      "image": "https://assets.tcgdex.net/es/sv/svp/019",
      "types": [
        "Agua"
      ],
      "illustrator": "Oswaldo KATO"
    }
  ]
}