{
  "name": "Clodsirede Paldea ex",
  "totalCards": 3,
  "cards": [
    {
      "id": "A2b-048",
      "name": "Clodsirede Paldea ex",
      "set": "A2b",
      "setName": "Festival Brillante",
      "number": "048",
      "rarity": "Cuatro Diamantes",
      "image": "https://assets.tcgdex.net/es/tcgp/A2b/048",
      "types": [
        "Oscura"
      ],
      "illustrator": "PLANETA Mochizuki"
    },
    {
      "id": "A2b-085",
      "name": "Clodsirede Paldea ex",
      "set": "A2b",
      "setName": "Festival Brillante",
      "number": "085",
      "rarity": "Dos Estrellas",
      "image": "https://assets.tcgdex.net/es/tcgp/A2b/085",
      "types": [
        "Oscura"
      ],
      "illustrator": "PLANETA Igarashi"
    },
    {
      "id": "A2b-093",
      "name": "Clodsirede Paldea ex",
      "set": "A2b",
      "setName": "Festival Brillante",
      "number": "093",
      "rarity": "Dos Estrellas",
      "image": "https://assets.tcgdex.net/es/tcgp/A2b/093",
      "types": [
        "Oscura"
      ],
      "illustrator": "REND"
    }
  ]
}