{
  "name": "Kilowattrel",
  "totalCards": 8,
  "cards": [
    {
      "id": "2023sv-8",
      "name": "Kilowattrel",
      "set": "2023sv",
      "setName": "Colección de McDonald's 2023",
      "number": "8",
      "rarity": "Ninguno",
      "image": null,
      "types": [
        "Rayo"
      ],
      "illustrator": "Kouki Saitou"
    },
    {
      "id": "B2a-044",
      "name": "Kilowattrel",
      "set": "B2a",
      "setName": "Paldean Wonders",
      "number": "044",
      "rarity": "Dos Diamantes",
      "image": null,
      "types": [
        "Rayo"
      ],
      "illustrator": "Pani Kobayashi"
    },
    {
      "id": "sv01-079",
      "name": "Kilowattrel",
      "set": "sv01",
      "setName": "Escarlata y Púrpura",
      "number": "079",
      "rarity": "Uncommon",
      "image": "https://assets.tcgdex.net/es/sv/sv01/079",
      "types": [
        "Rayo"
      ],
      "illustrator": "Kouki Saitou"
    },
    {
      "id": "sv02-082",
      "name": "Kilowattrel",
      "set": "sv02",
      "setName": "Evoluciones en Paldea",
      "number": "082",
      "rarity": "Uncommon",
      "image": "https://assets.tcgdex.net/es/sv/sv02/082",
      "types": [
        "Rayo"
      ],
      "illustrator": "Pani Kobayashi"
    },
    {
      "id": "sv04.5-022",
      "name": "Kilowattrel",
      "set": "sv04.5",
      "setName": "Destinos de Paldea",
      "number": "022",
      "rarity": "Uncommon",
      "image": "https://assets.tcgdex.net/es/sv/sv04.5/022",
      "types": [
        "Rayo"
      ],
      "illustrator": "AKIRA EGAWA"
    },
    {
      "id": "sv04.5-146",
      "name": "Kilowattrel",
      "set": "sv04.5",
      "setName": "Destinos de Paldea",
      "number": "146",
      "rarity": "Shiny rare",
      "image": "https://assets.tcgdex.net/es/sv/sv04.5/146",
      "types": [
        "Rayo"
      ],
      "illustrator": "Nisota Niso"
    },
    {
      "id": "sv06-076",
      "name": "Kilowattrel",
      "set": "sv06",
      "setName": "Mascarada Crepuscular",
      "number": "076",
      "rarity": "Uncommon",
      "image": "https://assets.tcgdex.net/es/sv/sv06/076",
      "types": [
        "Rayo"
      ],
      "illustrator": "Anesaki Dynamic"
    },
    {
      "id": "sv08-067",
      "name": "Kilowattrel",
      "set": "sv08",
      "setName": "Chispas Fulgurantes",
      "number": "067",
      "rarity": "Uncommon",
      "image": "https://assets.tcgdex.net/es/sv/sv08/067",
      "types": [
        "Rayo"
      ],
      "illustrator": "KEIICHIRO ITO"
    }
  ]
}