{
  "name": "Movimiento de Aza",
  "totalCards": 2,
  "cards": [
    {
      "id": "me02-090",
      "name": "Movimiento de Aza",
      "set": "me02",
      "setName": "Fuegos Fantasmales",
      "number": "090",
      "rarity": "Uncommon",
      "image": "https://assets.tcgdex.net/es/me/me02/090",
      "types": null,
      "illustrator": "GIDORA"
    },
    {
      "id": "me02-120",
      "name": "Movimiento de Aza",
      "set": "me02",
      "setName": "Fuegos Fantasmales",
      "number": "120",
      "rarity": "Ultra Rara",
      "image": "https://assets.tcgdex.net/es/me/me02/120",
      "types": null,
      "illustrator": "GIDORA"
    }
  ]
}