{
  "name": "Órdenes de Jefes",
  "totalCards": 13,
  "cards": [
    {
      "id": "me01-114",
      "name": "Órdenes de Jefes",
      "set": "me01",
      "setName": "Megaevolución",
      "number": "114",
      "rarity": "Uncommon",
      "image": "https://assets.tcgdex.net/es/me/me01/114",
      "types": null,
      "illustrator": "NC Empire"
    },
    {
      "id": "me02.5-183",
      "name": "Órdenes de Jefes",
      "set": "me02.5",
      "setName": "Héroes Ascendentes",
      "number": "183",
      "rarity": "Uncommon",
      "image": "https://assets.tcgdex.net/es/me/me02.5/183",
      "types": null,
      "illustrator": "akagi"
    },
    {
      "id": "me02.5-256",
      "name": "Órdenes de Jefes",
      "set": "me02.5",
      "setName": "Héroes Ascendentes",
      "number": "256",
      "rarity": "Ultra Rara",
      "image": "https://assets.tcgdex.net/es/me/me02.5/256",
      "types": null,
      "illustrator": "akagi"
    },
    {
      "id": "sv02-172",
      "name": "Órdenes de Jefes",
      "set": "sv02",
      "setName": "Evoluciones en Paldea",
      "number": "172",
      "rarity": "Rara",
      "image": "https://assets.tcgdex.net/es/sv/sv02/172",
      "types": null,
      "illustrator": "NC Empire"
    },
    {
      "id": "sv02-248",
      "name": "Órdenes de Jefes",
      "set": "sv02",
      "setName": "Evoluciones en Paldea",
      "number": "248",
      "rarity": "Ultra Rara",
      "image": "https://assets.tcgdex.net/es/sv/sv02/248",
      "types": null,
      "illustrator": "Hideki Ishikawa"
    },
    {
      "id": "sv02-265",
      "name": "Órdenes de Jefes",
      "set": "sv02",
      "setName": "Evoluciones en Paldea",
      "number": "265",
      "rarity": "Rara Ilustración Especial",
      "image": "https://assets.tcgdex.net/es/sv/sv02/265",
      "types": null,
      "illustrator": "hncl"
    },
    {
      "id": "swsh11-TG24",
      "name": "Órdenes de Jefes",
      "set": "swsh11",
      "setName": "Origen Perdido",
      "number": "TG24",
      "rarity": "Ultra Rara",
      "image": "https://assets.tcgdex.net/es/swsh/swsh11/TG24",
      "types": null,
      "illustrator": null
    },
    {
      "id": "swsh2-154",
      "name": "Órdenes de Jefes",
      "set": "swsh2",
      "setName": "Choque Rebelde",
      "number": "154",
      "rarity": "Holo Rara",
      "image": "https://assets.tcgdex.net/es/swsh/swsh2/154",
      "types": null,
      "illustrator": "nagimiso"
    },
    {
      "id": "swsh2-189",
      "name": "Órdenes de Jefes",
      "set": "swsh2",
      "setName": "Choque Rebelde",
      "number": "189",
      "rarity": "Ultra Rara",
      "image": "https://assets.tcgdex.net/es/swsh/swsh2/189",
      "types": null,
      "illustrator": "nagimiso"
    },
    {
      "id": "swsh2-200",
      "name": "Órdenes de Jefes",
      "set": "swsh2",
      "setName": "Choque Rebelde",
      "number": "200",
      "rarity": "Rara Secreta",
      "image": "https://assets.tcgdex.net/es/swsh/swsh2/200",
      "types": null,
      "illustrator": "nagimiso"
    },
    {
      "id": "swsh4.5-58",
      "name": "Órdenes de Jefes",
      "set": "swsh4.5",
      "setName": "Destinos Brillantes",
      "number": "58",
      "rarity": "Rara",
      "image": "https://assets.tcgdex.net/es/swsh/swsh4.5/58",
      "types": null,
      "illustrator": "Ryuta Fuse"
    },
    {
      "id": "swsh9-132",
      "name": "Órdenes de Jefes",
      "set": "swsh9",
      "setName": "Astros Brillantes",
      "number": "132",
      "rarity": "Holo Rara",
      "image": "https://assets.tcgdex.net/es/swsh/swsh9/132",
      "types": null,
      "illustrator": null
    },
    {
      "id": "swshp-SWSH251",
      "name": "Órdenes de Jefes",
      "set": "swshp",
      "setName": "Cartas de promoción ESES",
      "number": "SWSH251",
      "rarity": "Ninguno",
      "image": null,
      "types": null,
      "illustrator": "Mitsuhiro Arita"
    }
  ]
}