{
  "name": "Zyra",
  "totalCards": 2,
  "cards": [
    {
      "id": "sm3-127",
      "name": "Zyra",
      "set": "sm3",
      "setName": "Sombras Ardientes",
      "number": "127",
      "rarity": "Uncommon",
      "image": "https://assets.tcgdex.net/es/sm/sm3/127",
      "types": null,
      "illustrator": "take"
    },
    {
      "id": "sm3-147",
      "name": "Zyra",
      "set": "sm3",
      "setName": "Sombras Ardientes",
      "number": "147",
      "rarity": "Ultra Rara",
      "image": "https://assets.tcgdex.net/es/sm/sm3/147",
      "types": null,
      "illustrator": "Naoki Saito"
    }
  ]
}