{
  "name": "Sanosuke Sakuma",
  "totalCards": 189,
  "cards": [
    {
      "id": "2021swsh-25",
      "name": "Pikachu",
      "set": "2021swsh",
      "setName": "McDonald's Collection 2021",
      "number": "25",
      "rarity": "None",
      "image": null,
      "types": [
        "Lightning"
      ],
      "illustrator": "Sanosuke Sakuma"
    },
    {
      "id": "2024sv-12",
      "name": "Dragonite",
      "set": "2024sv",
      "setName": "McDonald's Collection 2024",
      "number": "12",
      "rarity": "None",
      "image": null,
      "types": [
        "Dragon"
      ],
      "illustrator": "Sanosuke Sakuma"
    },
    {
      "id": "A1-071",
      "name": "Seadra",
      "set": "A1",
      "setName": "Genetic Apex",
      "number": "071",
      "rarity": "Two Diamond",
      "image": "https://assets.tcgdex.net/en/tcgp/A1/071",
      "types": [
        "Water"
      ],
      "illustrator": "Sanosuke Sakuma"
    },
    {
      "id": "A1-114",
      "name": "Clefable",
      "set": "A1",
      "setName": "Genetic Apex",
      "number": "114",
      "rarity": "Two Diamond",
      "image": "https://assets.tcgdex.net/en/tcgp/A1/114",
      "types": [
        "Psychic"
      ],
      "illustrator": "Sanosuke Sakuma"
    },
    {
      "id": "A1-220",
      "name": "Misty",
      "set": "A1",
      "setName": "Genetic Apex",
      "number": "220",
      "rarity": "Two Diamond",
      "image": "https://assets.tcgdex.net/en/tcgp/A1/220",
      "types": null,
      "illustrator": "Sanosuke Sakuma"
    },
    {
      "id": "A1-267",
      "name": "Misty",
      "set": "A1",
      "setName": "Genetic Apex",
      "number": "267",
      "rarity": "Two Star",
      "image": "https://assets.tcgdex.net/en/tcgp/A1/267",
      "types": null,
      "illustrator": "Sanosuke Sakuma"
    },
    {
      "id": "A2-083",
      "name": "Gligar",
      "set": "A2",
      "setName": "Space-Time Smackdown",
      "number": "083",
      "rarity": "One Diamond",
      "image": "https://assets.tcgdex.net/en/tcgp/A2/083",
      "types": [
        "Fighting"
      ],
      "illustrator": "Sanosuke Sakuma"
    },
    {
      "id": "A2-138",
      "name": "Lopunny",
      "set": "A2",
      "setName": "Space-Time Smackdown",
      "number": "138",
      "rarity": "One Diamond",
      "image": "https://assets.tcgdex.net/en/tcgp/A2/138",
      "types": [
        "Colorless"
      ],
      "illustrator": "Sanosuke Sakuma"
    },
    {
      "id": "A2b-097",
      "name": "Weedle",
      "set": "A2b",
      "setName": "Shining Revelry",
      "number": "097",
      "rarity": "One Shiny",
      "image": "https://assets.tcgdex.net/en/tcgp/A2b/097",
      "types": [
        "Grass"
      ],
      "illustrator": "Sanosuke Sakuma"
    },
    {
      "id": "A2b-098",
      "name": "Kakuna",
      "set": "A2b",
      "setName": "Shining Revelry",
      "number": "098",
      "rarity": "One Shiny",
      "image": "https://assets.tcgdex.net/en/tcgp/A2b/098",
      "types": [
        "Grass"
      ],
      "illustrator": "Sanosuke Sakuma"
    },
    {
      "id": "A3-080",
      "name": "Comfey",
      "set": "A3",
      "setName": "Celestial Guardians",
      "number": "080",
      "rarity": "Three Diamond",
      "image": "https://assets.tcgdex.net/en/tcgp/A3/080",
      "types": [
        "Psychic"
      ],
      "illustrator": "Sanosuke Sakuma"
    },
    {
      "id": "A3-138",
      "name": "Stufful",
      "set": "A3",
      "setName": "Celestial Guardians",
      "number": "138",
      "rarity": "One Diamond",
      "image": "https://assets.tcgdex.net/en/tcgp/A3/138",
      "types": [
        "Colorless"
      ],
      "illustrator": "Sanosuke Sakuma"
    },
    {
      "id": "A3-226",
      "name": "Cubone",
      "set": "A3",
      "setName": "Celestial Guardians",
      "number": "226",
      "rarity": "One Shiny",
      "image": "https://assets.tcgdex.net/en/tcgp/A3/226",
      "types": [
        "Fighting"
      ],
      "illustrator": "Sanosuke Sakuma"
    },
    {
      "id": "A3-227",
      "name": "Marowak",
      "set": "A3",
      "setName": "Celestial Guardians",
      "number": "227",
      "rarity": "One Shiny",
      "image": "https://assets.tcgdex.net/en/tcgp/A3/227",
      "types": [
        "Fighting"
      ],
      "illustrator": "Sanosuke Sakuma"
    },
    {
      "id": "A3a-010",
      "name": "Mantine",
      "set": "A3a",
      "setName": "Extradimensional Crisis",
      "number": "010",
      "rarity": "One Diamond",
      "image": "https://assets.tcgdex.net/en/tcgp/A3a/010",
      "types": [
        "Water"
      ],
      "illustrator": "Sanosuke Sakuma"
    },
    {
      "id": "A3a-013",
      "name": "Shinx",
      "set": "A3a",
      "setName": "Extradimensional Crisis",
      "number": "013",
      "rarity": "One Diamond",
      "image": "https://assets.tcgdex.net/en/tcgp/A3a/013",
      "types": [
        "Lightning"
      ],
      "illustrator": "Sanosuke Sakuma"
    },
    {
      "id": "A3b-025",
      "name": "Jolteon",
      "set": "A3b",
      "setName": "Eevee Grove",
      "number": "025",
      "rarity": "Three Diamond",
      "image": "https://assets.tcgdex.net/en/tcgp/A3b/025",
      "types": [
        "Lightning"
      ],
      "illustrator": "Sanosuke Sakuma"
    },
    {
      "id": "A3b-054",
      "name": "Drampa",
      "set": "A3b",
      "setName": "Eevee Grove",
      "number": "054",
      "rarity": "Two Diamond",
      "image": "https://assets.tcgdex.net/en/tcgp/A3b/054",
      "types": [
        "Dragon"
      ],
      "illustrator": "Sanosuke Sakuma"
    },
    {
      "id": "A3b-097",
      "name": "Ralts",
      "set": "A3b",
      "setName": "Eevee Grove",
      "number": "097",
      "rarity": "One Shiny",
      "image": "https://assets.tcgdex.net/en/tcgp/A3b/097",
      "types": [
        "Psychic"
      ],
      "illustrator": "Sanosuke Sakuma"
    },
    {
      "id": "A3b-098",
      "name": "Kirlia",
      "set": "A3b",
      "setName": "Eevee Grove",
      "number": "098",
      "rarity": "One Shiny",
      "image": "https://assets.tcgdex.net/en/tcgp/A3b/098",
      "types": [
        "Psychic"
      ],
      "illustrator": "Sanosuke Sakuma"
    },
    {
      "id": "A3b-099",
      "name": "Gardevoir",
      "set": "A3b",
      "setName": "Eevee Grove",
      "number": "099",
      "rarity": "One Shiny",
      "image": "https://assets.tcgdex.net/en/tcgp/A3b/099",
      "types": [
        "Psychic"
      ],
      "illustrator": "Sanosuke Sakuma"
    },
    {
      "id": "A4-159",
      "name": "Fisher",
      "set": "A4",
      "setName": "Wisdom of Sea and Sky",
      "number": "159",
      "rarity": "Two Diamond",
      "image": "https://assets.tcgdex.net/en/tcgp/A4/159",
      "types": null,
      "illustrator": "Sanosuke Sakuma"
    },
    {
      "id": "A4-199",
      "name": "Fisher",
      "set": "A4",
      "setName": "Wisdom of Sea and Sky",
      "number": "199",
      "rarity": "Two Star",
      "image": "https://assets.tcgdex.net/en/tcgp/A4/199",
      "types": null,
      "illustrator": "Sanosuke Sakuma"
    },
    {
      "id": "B1-071",
      "name": "Froakie",
      "set": "B1",
      "setName": "Mega Rising",
      "number": "071",
      "rarity": "One Diamond",
      "image": "https://assets.tcgdex.net/en/tcgp/B1/071",
      "types": [
        "Water"
      ],
      "illustrator": "Sanosuke Sakuma"
    },
    {
      "id": "B1-097",
      "name": "Natu",
      "set": "B1",
      "setName": "Mega Rising",
      "number": "097",
      "rarity": "One Diamond",
      "image": "https://assets.tcgdex.net/en/tcgp/B1/097",
      "types": [
        "Psychic"
      ],
      "illustrator": "Sanosuke Sakuma"
    },
    {
      "id": "B1-106",
      "name": "Jirachi",
      "set": "B1",
      "setName": "Mega Rising",
      "number": "106",
      "rarity": "Three Diamond",
      "image": "https://assets.tcgdex.net/en/tcgp/B1/106",
      "types": [
        "Psychic"
      ],
      "illustrator": "Sanosuke Sakuma"
    },
    {
      "id": "B1-119",
      "name": "Carbink",
      "set": "B1",
      "setName": "Mega Rising",
      "number": "119",
      "rarity": "One Diamond",
      "image": "https://assets.tcgdex.net/en/tcgp/B1/119",
      "types": [
        "Psychic"
      ],
      "illustrator": "Sanosuke Sakuma"
    },
    {
      "id": "B1-223",
      "name": "May",
      "set": "B1",
      "setName": "Mega Rising",
      "number": "223",
      "rarity": "Two Diamond",
      "image": "https://assets.tcgdex.net/en/tcgp/B1/223",
      "types": null,
      "illustrator": "Sanosuke Sakuma"
    },
    {
      "id": "B1-268",
      "name": "May",
      "set": "B1",
      "setName": "Mega Rising",
      "number": "268",
      "rarity": "Two Star",
      "image": "https://assets.tcgdex.net/en/tcgp/B1/268",
      "types": null,
      "illustrator": "Sanosuke Sakuma"
    },
    {
      "id": "B1a-064",
      "name": "Bouffalant",
      "set": "B1a",
      "setName": "Crimson Blaze",
      "number": "064",
      "rarity": "Two Diamond",
      "image": "https://assets.tcgdex.net/en/tcgp/B1a/064",
      "types": [
        "Colorless"
      ],
      "illustrator": "Sanosuke Sakuma"
    },
    {
      "id": "B2-045",
      "name": "Cramorant",
      "set": "B2",
      "setName": "Fantastical Parade",
      "number": "045",
      "rarity": "One Diamond",
      "image": "https://assets.tcgdex.net/en/tcgp/B2/045",
      "types": [
        "Water"
      ],
      "illustrator": "Sanosuke Sakuma"
    },
    {
      "id": "B2a-051",
      "name": "Espathra",
      "set": "B2a",
      "setName": "Paldean Wonders",
      "number": "051",
      "rarity": "Two Diamond",
      "image": null,
      "types": [
        "Psychic"
      ],
      "illustrator": "Sanosuke Sakuma"
    },
    {
      "id": "B2a-089",
      "name": "Iono",
      "set": "B2a",
      "setName": "Paldean Wonders",
      "number": "089",
      "rarity": "Two Diamond",
      "image": null,
      "types": null,
      "illustrator": "Sanosuke Sakuma"
    },
    {
      "id": "B2a-090",
      "name": "Nemona",
      "set": "B2a",
      "setName": "Paldean Wonders",
      "number": "090",
      "rarity": "Two Diamond",
      "image": null,
      "types": null,
      "illustrator": "Sanosuke Sakuma"
    },
    {
      "id": "B2a-106",
      "name": "Iono",
      "set": "B2a",
      "setName": "Paldean Wonders",
      "number": "106",
      "rarity": "Two Star",
      "image": null,
      "types": null,
      "illustrator": "Sanosuke Sakuma"
    },
    {
      "id": "B2a-107",
      "name": "Nemona",
      "set": "B2a",
      "setName": "Paldean Wonders",
      "number": "107",
      "rarity": "Two Star",
      "image": null,
      "types": null,
      "illustrator": "Sanosuke Sakuma"
    },
    {
      "id": "bw11-107",
      "name": "Bouffalant",
      "set": "bw11",
      "setName": "Legendary Treasures",
      "number": "107",
      "rarity": "Uncommon",
      "image": "https://assets.tcgdex.net/en/bw/bw11/107",
      "types": [
        "Colorless"
      ],
      "illustrator": "Sanosuke Sakuma"
    },
    {
      "id": "bw11-55",
      "name": "Natu",
      "set": "bw11",
      "setName": "Legendary Treasures",
      "number": "55",
      "rarity": "Common",
      "image": "https://assets.tcgdex.net/en/bw/bw11/55",
      "types": [
        "Psychic"
      ],
      "illustrator": "Sanosuke Sakuma"
    },
    {
      "id": "bw11-62",
      "name": "Croagunk",
      "set": "bw11",
      "setName": "Legendary Treasures",
      "number": "62",
      "rarity": "Common",
      "image": "https://assets.tcgdex.net/en/bw/bw11/62",
      "types": [
        "Psychic"
      ],
      "illustrator": "Sanosuke Sakuma"
    },
    {
      "id": "bw11-RC16",
      "name": "Ursaring",
      "set": "bw11",
      "setName": "Legendary Treasures",
      "number": "RC16",
      "rarity": "Common",
      "image": "https://assets.tcgdex.net/en/bw/bw11/RC16",
      "types": [
        "Colorless"
      ],
      "illustrator": "Sanosuke Sakuma"
    },
    {
      "id": "bw11-RC4",
      "name": "Growlithe",
      "set": "bw11",
      "setName": "Legendary Treasures",
      "number": "RC4",
      "rarity": "Uncommon",
      "image": "https://assets.tcgdex.net/en/bw/bw11/RC4",
      "types": [
        "Fire"
      ],
      "illustrator": "Sanosuke Sakuma"
    },
    {
      "id": "dc1-20",
      "name": "Team Aqua's Carvanha",
      "set": "dc1",
      "setName": "Double Crisis",
      "number": "20",
      "rarity": "Common",
      "image": "https://assets.tcgdex.net/en/xy/dc1/20",
      "types": [
        "Darkness"
      ],
      "illustrator": "Sanosuke Sakuma"
    },
    {
      "id": "dc1-3",
      "name": "Team Aqua's Spheal",
      "set": "dc1",
      "setName": "Double Crisis",
      "number": "3",
      "rarity": "Common",
      "image": "https://assets.tcgdex.net/en/xy/dc1/3",
      "types": [
        "Water"
      ],
      "illustrator": "Sanosuke Sakuma"
    },
    {
      "id": "g1-RC1",
      "name": "Chikorita",
      "set": "g1",
      "setName": "Generations",
      "number": "RC1",
      "rarity": "Common",
      "image": "https://assets.tcgdex.net/en/xy/g1/RC1",
      "types": [
        "Grass"
      ],
      "illustrator": "Sanosuke Sakuma"
    },
    {
      "id": "me01-033",
      "name": "Corphish",
      "set": "me01",
      "setName": "Mega Evolution",
      "number": "033",
      "rarity": "Common",
      "image": "https://assets.tcgdex.net/en/me/me01/033",
      "types": [
        "Water"
      ],
      "illustrator": "Sanosuke Sakuma"
    },
    {
      "id": "me02.5-023",
      "name": "Ethan's Slugma",
      "set": "me02.5",
      "setName": "Ascended Heroes",
      "number": "023",
      "rarity": "Common",
      "image": "https://assets.tcgdex.net/en/me/me02.5/023",
      "types": [
        "Fire"
      ],
      "illustrator": "Sanosuke Sakuma"
    },
    {
      "id": "me02.5-182",
      "name": "Anthea & Concordia",
      "set": "me02.5",
      "setName": "Ascended Heroes",
      "number": "182",
      "rarity": "Uncommon",
      "image": "https://assets.tcgdex.net/en/me/me02.5/182",
      "types": null,
      "illustrator": "Sanosuke Sakuma"
    },
    {
      "id": "me02.5-254",
      "name": "Anthea & Concordia",
      "set": "me02.5",
      "setName": "Ascended Heroes",
      "number": "254",
      "rarity": "Ultra Rare",
      "image": "https://assets.tcgdex.net/en/me/me02.5/254",
      "types": null,
      "illustrator": "Sanosuke Sakuma"
    },
    {
      "id": "P-A-019",
      "name": "Greninja",
      "set": "P-A",
      "setName": "Promos-A",
      "number": "019",
      "rarity": "None",
      "image": "https://assets.tcgdex.net/en/tcgp/P-A/019",
      "types": [
        "Water"
      ],
      "illustrator": "Sanosuke Sakuma"
    },
    {
      "id": "P-A-061",
      "name": "Froakie",
      "set": "P-A",
      "setName": "Promos-A",
      "number": "061",
      "rarity": "One Diamond",
      "image": "https://assets.tcgdex.net/en/tcgp/P-A/061",
      "types": [
        "Water"
      ],
      "illustrator": "Sanosuke Sakuma"
    },
    {
      "id": "sm11-107",
      "name": "Heracross",
      "set": "sm11",
      "setName": "Unified Minds",
      "number": "107",
      "rarity": "Uncommon",
      "image": "https://assets.tcgdex.net/en/sm/sm11/107",
      "types": [
        "Fighting"
      ],
      "illustrator": "Sanosuke Sakuma"
    },
    {
      "id": "sm1-111",
      "name": "Stufful",
      "set": "sm1",
      "setName": "Sun & Moon",
      "number": "111",
      "rarity": "Common",
      "image": "https://assets.tcgdex.net/en/sm/sm1/111",
      "types": [
        "Colorless"
      ],
      "illustrator": "Sanosuke Sakuma"
    },
    {
      "id": "sm11-149",
      "name": "Dragonair",
      "set": "sm11",
      "setName": "Unified Minds",
      "number": "149",
      "rarity": "Uncommon",
      "image": "https://assets.tcgdex.net/en/sm/sm11/149",
      "types": [
        "Dragon"
      ],
      "illustrator": "Sanosuke Sakuma"
    },
    {
      "id": "sm11-163",
      "name": "Kangaskhan",
      "set": "sm11",
      "setName": "Unified Minds",
      "number": "163",
      "rarity": "Rare",
      "image": "https://assets.tcgdex.net/en/sm/sm11/163",
      "types": [
        "Colorless"
      ],
      "illustrator": "Sanosuke Sakuma"
    },
    {
      "id": "sm1-146",
      "name": "Ilima",
      "set": "sm1",
      "setName": "Sun & Moon",
      "number": "146",
      "rarity": "Ultra Rare",
      "image": "https://assets.tcgdex.net/en/sm/sm1/146",
      "types": null,
      "illustrator": "Sanosuke Sakuma"
    },
    {
      "id": "sm1-149",
      "name": "Team Skull Grunt",
      "set": "sm1",
      "setName": "Sun & Moon",
      "number": "149",
      "rarity": "Ultra Rare",
      "image": "https://assets.tcgdex.net/en/sm/sm1/149",
      "types": null,
      "illustrator": "Sanosuke Sakuma"
    },
    {
      "id": "sm11-55",
      "name": "Pikachu",
      "set": "sm11",
      "setName": "Unified Minds",
      "number": "55",
      "rarity": "Common",
      "image": "https://assets.tcgdex.net/en/sm/sm11/55",
      "types": [
        "Lightning"
      ],
      "illustrator": "Sanosuke Sakuma"
    },
    {
      "id": "sm115-56",
      "name": "Erika’s Hospitality",
      "set": "sm115",
      "setName": "Hidden Fates",
      "number": "56",
      "rarity": "Rare",
      "image": "https://assets.tcgdex.net/en/sm/sm115/56",
      "types": null,
      "illustrator": "Sanosuke Sakuma"
    },
    {
      "id": "sm1-65",
      "name": "Cosmoem",
      "set": "sm1",
      "setName": "Sun & Moon",
      "number": "65",
      "rarity": "Rare",
      "image": "https://assets.tcgdex.net/en/sm/sm1/65",
      "types": [
        "Psychic"
      ],
      "illustrator": "Sanosuke Sakuma"
    },
    {
      "id": "sm2-144",
      "name": "Hau",
      "set": "sm2",
      "setName": "Guardians Rising",
      "number": "144",
      "rarity": "Ultra Rare",
      "image": "https://assets.tcgdex.net/en/sm/sm2/144",
      "types": null,
      "illustrator": "Sanosuke Sakuma"
    },
    {
      "id": "sm2-37",
      "name": "Wishiwashi",
      "set": "sm2",
      "setName": "Guardians Rising",
      "number": "37",
      "rarity": "Common",
      "image": "https://assets.tcgdex.net/en/sm/sm2/37",
      "types": [
        "Water"
      ],
      "illustrator": "Sanosuke Sakuma"
    },
    {
      "id": "sm2-6",
      "name": "Phantump",
      "set": "sm2",
      "setName": "Guardians Rising",
      "number": "6",
      "rarity": "Common",
      "image": "https://assets.tcgdex.net/en/sm/sm2/6",
      "types": [
        "Grass"
      ],
      "illustrator": "Sanosuke Sakuma"
    },
    {
      "id": "sm2-93",
      "name": "Comfey",
      "set": "sm2",
      "setName": "Guardians Rising",
      "number": "93",
      "rarity": "Rare",
      "image": "https://assets.tcgdex.net/en/sm/sm2/93",
      "types": [
        "Fairy"
      ],
      "illustrator": "Sanosuke Sakuma"
    },
    {
      "id": "sm3.5-40",
      "name": "Shining Mew",
      "set": "sm3.5",
      "setName": "Shining Legends",
      "number": "40",
      "rarity": "Ultra Rare",
      "image": null,
      "types": [
        "Psychic"
      ],
      "illustrator": "Sanosuke Sakuma"
    },
    {
      "id": "sm3.5-73",
      "name": "Pokémon Breeder",
      "set": "sm3.5",
      "setName": "Shining Legends",
      "number": "73",
      "rarity": "Ultra Rare",
      "image": null,
      "types": null,
      "illustrator": "Sanosuke Sakuma"
    },
    {
      "id": "sm3-145",
      "name": "Plumeria",
      "set": "sm3",
      "setName": "Burning Shadows",
      "number": "145",
      "rarity": "Ultra Rare",
      "image": "https://assets.tcgdex.net/en/sm/sm3/145",
      "types": null,
      "illustrator": "Sanosuke Sakuma"
    },
    {
      "id": "sm3-146",
      "name": "Sophocles",
      "set": "sm3",
      "setName": "Burning Shadows",
      "number": "146",
      "rarity": "Ultra Rare",
      "image": "https://assets.tcgdex.net/en/sm/sm3/146",
      "types": null,
      "illustrator": "Sanosuke Sakuma"
    },
    {
      "id": "sm3-37",
      "name": "Simipour",
      "set": "sm3",
      "setName": "Burning Shadows",
      "number": "37",
      "rarity": "Uncommon",
      "image": "https://assets.tcgdex.net/en/sm/sm3/37",
      "types": [
        "Water"
      ],
      "illustrator": "Sanosuke Sakuma"
    },
    {
      "id": "sm3-66",
      "name": "Rhydon",
      "set": "sm3",
      "setName": "Burning Shadows",
      "number": "66",
      "rarity": "Uncommon",
      "image": "https://assets.tcgdex.net/en/sm/sm3/66",
      "types": [
        "Fighting"
      ],
      "illustrator": "Sanosuke Sakuma"
    },
    {
      "id": "sm5-125",
      "name": "Lillie",
      "set": "sm5",
      "setName": "Ultra Prism",
      "number": "125",
      "rarity": "Uncommon",
      "image": "https://assets.tcgdex.net/en/sm/sm5/125",
      "types": null,
      "illustrator": "Sanosuke Sakuma"
    },
    {
      "id": "sm5-133",
      "name": "Pokémon Fan Club",
      "set": "sm5",
      "setName": "Ultra Prism",
      "number": "133",
      "rarity": "Uncommon",
      "image": "https://assets.tcgdex.net/en/sm/sm5/133",
      "types": null,
      "illustrator": "Sanosuke Sakuma"
    },
    {
      "id": "sm5-155",
      "name": "Pokémon Fan Club",
      "set": "sm5",
      "setName": "Ultra Prism",
      "number": "155",
      "rarity": "Ultra Rare",
      "image": "https://assets.tcgdex.net/en/sm/sm5/155",
      "types": null,
      "illustrator": "Sanosuke Sakuma"
    },
    {
      "id": "sm5-61",
      "name": "Cosmoem",
      "set": "sm5",
      "setName": "Ultra Prism",
      "number": "61",
      "rarity": "Uncommon",
      "image": "https://assets.tcgdex.net/en/sm/sm5/61",
      "types": [
        "Psychic"
      ],
      "illustrator": "Sanosuke Sakuma"
    },
    {
      "id": "sm6-108",
      "name": "Judge",
      "set": "sm6",
      "setName": "Forbidden Light",
      "number": "108",
      "rarity": "Uncommon",
      "image": "https://assets.tcgdex.net/en/sm/sm6/108",
      "types": null,
      "illustrator": "Sanosuke Sakuma"
    },
    {
      "id": "sm7.5-51",
      "name": "Drampa",
      "set": "sm7.5",
      "setName": "Dragon Majesty",
      "number": "51",
      "rarity": "Uncommon",
      "image": null,
      "types": [
        "Dragon"
      ],
      "illustrator": "Sanosuke Sakuma"
    },
    {
      "id": "sm7-162",
      "name": "Bill’s Maintenance",
      "set": "sm7",
      "setName": "Celestial Storm",
      "number": "162",
      "rarity": "Ultra Rare",
      "image": "https://assets.tcgdex.net/en/sm/sm7/162",
      "types": null,
      "illustrator": "Sanosuke Sakuma"
    },
    {
      "id": "sm7-52",
      "name": "Manectric",
      "set": "sm7",
      "setName": "Celestial Storm",
      "number": "52",
      "rarity": "Rare",
      "image": "https://assets.tcgdex.net/en/sm/sm7/52",
      "types": [
        "Lightning"
      ],
      "illustrator": "Sanosuke Sakuma"
    },
    {
      "id": "sm8-105",
      "name": "Mareanie",
      "set": "sm8",
      "setName": "Lost Thunder",
      "number": "105",
      "rarity": "Common",
      "image": "https://assets.tcgdex.net/en/sm/sm8/105",
      "types": [
        "Psychic"
      ],
      "illustrator": "Sanosuke Sakuma"
    },
    {
      "id": "sm8-117",
      "name": "Carbink",
      "set": "sm8",
      "setName": "Lost Thunder",
      "number": "117",
      "rarity": "Common",
      "image": "https://assets.tcgdex.net/en/sm/sm8/117",
      "types": [
        "Fighting"
      ],
      "illustrator": "Sanosuke Sakuma"
    },
    {
      "id": "sm8-209",
      "name": "Judge",
      "set": "sm8",
      "setName": "Lost Thunder",
      "number": "209",
      "rarity": "Ultra Rare",
      "image": "https://assets.tcgdex.net/en/sm/sm8/209",
      "types": null,
      "illustrator": "Sanosuke Sakuma"
    },
    {
      "id": "sm8-212",
      "name": "Morty",
      "set": "sm8",
      "setName": "Lost Thunder",
      "number": "212",
      "rarity": "Ultra Rare",
      "image": "https://assets.tcgdex.net/en/sm/sm8/212",
      "types": null,
      "illustrator": "Sanosuke Sakuma"
    },
    {
      "id": "sm8-214",
      "name": "Whitney",
      "set": "sm8",
      "setName": "Lost Thunder",
      "number": "214",
      "rarity": "Ultra Rare",
      "image": "https://assets.tcgdex.net/en/sm/sm8/214",
      "types": null,
      "illustrator": "Sanosuke Sakuma"
    },
    {
      "id": "sm8-58",
      "name": "Mantine",
      "set": "sm8",
      "setName": "Lost Thunder",
      "number": "58",
      "rarity": "Uncommon",
      "image": "https://assets.tcgdex.net/en/sm/sm8/58",
      "types": [
        "Water"
      ],
      "illustrator": "Sanosuke Sakuma"
    },
    {
      "id": "sm9-115",
      "name": "Alolan Exeggutor",
      "set": "sm9",
      "setName": "Team Up",
      "number": "115",
      "rarity": "Rare",
      "image": "https://assets.tcgdex.net/en/sm/sm9/115",
      "types": [
        "Dragon"
      ],
      "illustrator": "Sanosuke Sakuma"
    },
    {
      "id": "sm9-140",
      "name": "Erika’s Hospitality",
      "set": "sm9",
      "setName": "Team Up",
      "number": "140",
      "rarity": "Rare",
      "image": "https://assets.tcgdex.net/en/sm/sm9/140",
      "types": null,
      "illustrator": "Sanosuke Sakuma"
    },
    {
      "id": "sm9-170",
      "name": "Latias & Latios GX",
      "set": "sm9",
      "setName": "Team Up",
      "number": "170",
      "rarity": "Ultra Rare",
      "image": "https://assets.tcgdex.net/en/sm/sm9/170",
      "types": [
        "Dragon"
      ],
      "illustrator": "Sanosuke Sakuma"
    },
    {
      "id": "sm9-174",
      "name": "Erika’s Hospitality",
      "set": "sm9",
      "setName": "Team Up",
      "number": "174",
      "rarity": "Ultra Rare",
      "image": "https://assets.tcgdex.net/en/sm/sm9/174",
      "types": null,
      "illustrator": "Sanosuke Sakuma"
    },
    {
      "id": "sm9-21",
      "name": "Torracat",
      "set": "sm9",
      "setName": "Team Up",
      "number": "21",
      "rarity": "Uncommon",
      "image": "https://assets.tcgdex.net/en/sm/sm9/21",
      "types": [
        "Fire"
      ],
      "illustrator": "Sanosuke Sakuma"
    },
    {
      "id": "smp-SM44",
      "name": "Togedemaru",
      "set": "smp",
      "setName": "SM Black Star Promos",
      "number": "SM44",
      "rarity": "Rare",
      "image": "https://assets.tcgdex.net/en/sm/smp/SM44",
      "types": [
        "Lightning"
      ],
      "illustrator": "Sanosuke Sakuma"
    },
    {
      "id": "smp-SM79",
      "name": "Shining Celebi",
      "set": "smp",
      "setName": "SM Black Star Promos",
      "number": "SM79",
      "rarity": "Rare",
      "image": "https://assets.tcgdex.net/en/sm/smp/SM79",
      "types": [
        "Grass"
      ],
      "illustrator": "Sanosuke Sakuma"
    },
    {
      "id": "smp-SM81",
      "name": "Pikachu",
      "set": "smp",
      "setName": "SM Black Star Promos",
      "number": "SM81",
      "rarity": "Rare",
      "image": "https://assets.tcgdex.net/en/sm/smp/SM81",
      "types": [
        "Lightning"
      ],
      "illustrator": "Sanosuke Sakuma"
    },
    {
      "id": "smp-SM92",
      "name": "Tapu Fini",
      "set": "smp",
      "setName": "SM Black Star Promos",
      "number": "SM92",
      "rarity": "Rare",
      "image": "https://assets.tcgdex.net/en/sm/smp/SM92",
      "types": [
        "Water"
      ],
      "illustrator": "Sanosuke Sakuma"
    },
    {
      "id": "sv01-179",
      "name": "Miriam",
      "set": "sv01",
      "setName": "Scarlet & Violet",
      "number": "179",
      "rarity": "Uncommon",
      "image": "https://assets.tcgdex.net/en/sv/sv01/179",
      "types": null,
      "illustrator": "Sanosuke Sakuma"
    },
    {
      "id": "sv01-180",
      "name": "Nemona",
      "set": "sv01",
      "setName": "Scarlet & Violet",
      "number": "180",
      "rarity": "Common",
      "image": "https://assets.tcgdex.net/en/sv/sv01/180",
      "types": null,
      "illustrator": "Sanosuke Sakuma"
    },
    {
      "id": "sv01-238",
      "name": "Miriam",
      "set": "sv01",
      "setName": "Scarlet & Violet",
      "number": "238",
      "rarity": "Ultra Rare",
      "image": "https://assets.tcgdex.net/en/sv/sv01/238",
      "types": null,
      "illustrator": "Sanosuke Sakuma"
    },
    {
      "id": "sv02-185",
      "name": "Iono",
      "set": "sv02",
      "setName": "Paldea Evolved",
      "number": "185",
      "rarity": "Uncommon",
      "image": "https://assets.tcgdex.net/en/sv/sv02/185",
      "types": null,
      "illustrator": "Sanosuke Sakuma"
    },
    {
      "id": "sv02-249",
      "name": "Clavell",
      "set": "sv02",
      "setName": "Paldea Evolved",
      "number": "249",
      "rarity": "Ultra Rare",
      "image": "https://assets.tcgdex.net/en/sv/sv02/249",
      "types": null,
      "illustrator": "Sanosuke Sakuma"
    },
    {
      "id": "sv02-254",
      "name": "Iono",
      "set": "sv02",
      "setName": "Paldea Evolved",
      "number": "254",
      "rarity": "Ultra Rare",
      "image": "https://assets.tcgdex.net/en/sv/sv02/254",
      "types": null,
      "illustrator": "Sanosuke Sakuma"
    },
    {
      "id": "sv02-270",
      "name": "Saguaro",
      "set": "sv02",
      "setName": "Paldea Evolved",
      "number": "270",
      "rarity": "Special illustration rare",
      "image": "https://assets.tcgdex.net/en/sv/sv02/270",
      "types": null,
      "illustrator": "Sanosuke Sakuma"
    },
    {
      "id": "sv03.5-147",
      "name": "Dratini",
      "set": "sv03.5",
      "setName": "151",
      "number": "147",
      "rarity": "Common",
      "image": "https://assets.tcgdex.net/en/sv/sv03.5/147",
      "types": [
        "Dragon"
      ],
      "illustrator": "Sanosuke Sakuma"
    },
    {
      "id": "sv03.5-148",
      "name": "Dragonair",
      "set": "sv03.5",
      "setName": "151",
      "number": "148",
      "rarity": "Uncommon",
      "image": "https://assets.tcgdex.net/en/sv/sv03.5/148",
      "types": [
        "Dragon"
      ],
      "illustrator": "Sanosuke Sakuma"
    },
    {
      "id": "sv03.5-149",
      "name": "Dragonite",
      "set": "sv03.5",
      "setName": "151",
      "number": "149",
      "rarity": "Rare",
      "image": "https://assets.tcgdex.net/en/sv/sv03.5/149",
      "types": [
        "Dragon"
      ],
      "illustrator": "Sanosuke Sakuma"
    },
    {
      "id": "sv03-121",
      "name": "Glimmet",
      "set": "sv03",
      "setName": "Obsidian Flames",
      "number": "121",
      "rarity": "Common",
      "image": "https://assets.tcgdex.net/en/sv/sv03/121",
      "types": [
        "Fighting"
      ],
      "illustrator": "Sanosuke Sakuma"
    },
    {
      "id": "sv04.5-052",
      "name": "Grapploct",
      "set": "sv04.5",
      "setName": "Paldean Fates",
      "number": "052",
      "rarity": "Uncommon",
      "image": "https://assets.tcgdex.net/en/sv/sv04.5/052",
      "types": [
        "Fighting"
      ],
      "illustrator": "Sanosuke Sakuma"
    },
    {
      "id": "sv04.5-080",
      "name": "Iono",
      "set": "sv04.5",
      "setName": "Paldean Fates",
      "number": "080",
      "rarity": "Uncommon",
      "image": "https://assets.tcgdex.net/en/sv/sv04.5/080",
      "types": null,
      "illustrator": "Sanosuke Sakuma"
    },
    {
      "id": "sv04.5-082",
      "name": "Nemona",
      "set": "sv04.5",
      "setName": "Paldean Fates",
      "number": "082",
      "rarity": "Common",
      "image": "https://assets.tcgdex.net/en/sv/sv04.5/082",
      "types": null,
      "illustrator": "Sanosuke Sakuma"
    },
    {
      "id": "sv04.5-132",
      "name": "Raichu",
      "set": "sv04.5",
      "setName": "Paldean Fates",
      "number": "132",
      "rarity": "Shiny rare",
      "image": "https://assets.tcgdex.net/en/sv/sv04.5/132",
      "types": [
        "Lightning"
      ],
      "illustrator": "Sanosuke Sakuma"
    },
    {
      "id": "sv04.5-161",
      "name": "Dachsbun",
      "set": "sv04.5",
      "setName": "Paldean Fates",
      "number": "161",
      "rarity": "Shiny rare",
      "image": "https://assets.tcgdex.net/en/sv/sv04.5/161",
      "types": [
        "Psychic"
      ],
      "illustrator": "Sanosuke Sakuma"
    },
    {
      "id": "sv04.5-205",
      "name": "Skwovet",
      "set": "sv04.5",
      "setName": "Paldean Fates",
      "number": "205",
      "rarity": "Shiny rare",
      "image": "https://assets.tcgdex.net/en/sv/sv04.5/205",
      "types": [
        "Colorless"
      ],
      "illustrator": "Sanosuke Sakuma"
    },
    {
      "id": "sv04.5-229",
      "name": "Nemona",
      "set": "sv04.5",
      "setName": "Paldean Fates",
      "number": "229",
      "rarity": "Ultra Rare",
      "image": "https://assets.tcgdex.net/en/sv/sv04.5/229",
      "types": null,
      "illustrator": "Sanosuke Sakuma"
    },
    {
      "id": "sv05-128",
      "name": "Dunsparce",
      "set": "sv05",
      "setName": "Temporal Forces",
      "number": "128",
      "rarity": "Common",
      "image": "https://assets.tcgdex.net/en/sv/sv05/128",
      "types": [
        "Colorless"
      ],
      "illustrator": "Sanosuke Sakuma"
    },
    {
      "id": "sv06-024",
      "name": "Teal Mask Ogerpon",
      "set": "sv06",
      "setName": "Twilight Masquerade",
      "number": "024",
      "rarity": "Rare",
      "image": "https://assets.tcgdex.net/en/sv/sv06/024",
      "types": [
        "Grass"
      ],
      "illustrator": "Sanosuke Sakuma"
    },
    {
      "id": "sv06-078",
      "name": "Clefairy",
      "set": "sv06",
      "setName": "Twilight Masquerade",
      "number": "078",
      "rarity": "Common",
      "image": "https://assets.tcgdex.net/en/sv/sv06/078",
      "types": [
        "Psychic"
      ],
      "illustrator": "Sanosuke Sakuma"
    },
    {
      "id": "sv07-139",
      "name": "Lacey",
      "set": "sv07",
      "setName": "Stellar Crown",
      "number": "139",
      "rarity": "Uncommon",
      "image": "https://assets.tcgdex.net/en/sv/sv07/139",
      "types": null,
      "illustrator": "Sanosuke Sakuma"
    },
    {
      "id": "sv07-166",
      "name": "Lacey",
      "set": "sv07",
      "setName": "Stellar Crown",
      "number": "166",
      "rarity": "Ultra Rare",
      "image": "https://assets.tcgdex.net/en/sv/sv07/166",
      "types": null,
      "illustrator": "Sanosuke Sakuma"
    },
    {
      "id": "sv08.5-079",
      "name": "Dunsparce",
      "set": "sv08.5",
      "setName": "Prismatic Evolutions",
      "number": "079",
      "rarity": "Common",
      "image": "https://assets.tcgdex.net/en/sv/sv08.5/079",
      "types": [
        "Colorless"
      ],
      "illustrator": "Sanosuke Sakuma"
    },
    {
      "id": "sv08.5-114",
      "name": "Lacey",
      "set": "sv08.5",
      "setName": "Prismatic Evolutions",
      "number": "114",
      "rarity": "Uncommon",
      "image": "https://assets.tcgdex.net/en/sv/sv08.5/114",
      "types": null,
      "illustrator": "Sanosuke Sakuma"
    },
    {
      "id": "sv08-063",
      "name": "Zebstrika",
      "set": "sv08",
      "setName": "Surging Sparks",
      "number": "063",
      "rarity": "Common",
      "image": "https://assets.tcgdex.net/en/sv/sv08/063",
      "types": [
        "Lightning"
      ],
      "illustrator": "Sanosuke Sakuma"
    },
    {
      "id": "sv08-187",
      "name": "Surfer",
      "set": "sv08",
      "setName": "Surging Sparks",
      "number": "187",
      "rarity": "Uncommon",
      "image": "https://assets.tcgdex.net/en/sv/sv08/187",
      "types": null,
      "illustrator": "Sanosuke Sakuma"
    },
    {
      "id": "sv08-235",
      "name": "Surfer",
      "set": "sv08",
      "setName": "Surging Sparks",
      "number": "235",
      "rarity": "Ultra Rare",
      "image": "https://assets.tcgdex.net/en/sv/sv08/235",
      "types": null,
      "illustrator": "Sanosuke Sakuma"
    },
    {
      "id": "sv09-070",
      "name": "Dhelmise",
      "set": "sv09",
      "setName": "Journey Together",
      "number": "070",
      "rarity": "Common",
      "image": "https://assets.tcgdex.net/en/sv/sv09/070",
      "types": [
        "Psychic"
      ],
      "illustrator": "Sanosuke Sakuma"
    },
    {
      "id": "sv09-087",
      "name": "Hop's Sandaconda",
      "set": "sv09",
      "setName": "Journey Together",
      "number": "087",
      "rarity": "Uncommon",
      "image": "https://assets.tcgdex.net/en/sv/sv09/087",
      "types": [
        "Fighting"
      ],
      "illustrator": "Sanosuke Sakuma"
    },
    {
      "id": "sv09-142",
      "name": "Billy & O'Nare",
      "set": "sv09",
      "setName": "Journey Together",
      "number": "142",
      "rarity": "Common",
      "image": "https://assets.tcgdex.net/en/sv/sv09/142",
      "types": null,
      "illustrator": "Sanosuke Sakuma"
    },
    {
      "id": "sv10-035",
      "name": "Ethan's Slugma",
      "set": "sv10",
      "setName": "Destined Rivals",
      "number": "035",
      "rarity": "Common",
      "image": "https://assets.tcgdex.net/en/sv/sv10/035",
      "types": [
        "Fire"
      ],
      "illustrator": "Sanosuke Sakuma"
    },
    {
      "id": "sv10-151",
      "name": "Kangaskhan",
      "set": "sv10",
      "setName": "Destined Rivals",
      "number": "151",
      "rarity": "Common",
      "image": "https://assets.tcgdex.net/en/sv/sv10/151",
      "types": [
        "Colorless"
      ],
      "illustrator": "Sanosuke Sakuma"
    },
    {
      "id": "svp-010",
      "name": "Espathra",
      "set": "svp",
      "setName": "SVP Black Star Promos",
      "number": "010",
      "rarity": "None",
      "image": "https://assets.tcgdex.net/en/sv/svp/010",
      "types": [
        "Psychic"
      ],
      "illustrator": "Sanosuke Sakuma"
    },
    {
      "id": "swsh3.5-53",
      "name": "Hop",
      "set": "swsh3.5",
      "setName": "Champion's Path",
      "number": "53",
      "rarity": "Uncommon",
      "image": "https://assets.tcgdex.net/en/swsh/swsh3.5/53",
      "types": null,
      "illustrator": "Sanosuke Sakuma"
    },
    {
      "id": "swsh3-45",
      "name": "Vanillite",
      "set": "swsh3",
      "setName": "Darkness Ablaze",
      "number": "45",
      "rarity": "Common",
      "image": "https://assets.tcgdex.net/en/swsh/swsh3/45",
      "types": [
        "Water"
      ],
      "illustrator": "Sanosuke Sakuma"
    },
    {
      "id": "swsh3-86",
      "name": "Larvitar",
      "set": "swsh3",
      "setName": "Darkness Ablaze",
      "number": "86",
      "rarity": "Common",
      "image": "https://assets.tcgdex.net/en/swsh/swsh3/86",
      "types": [
        "Fighting"
      ],
      "illustrator": "Sanosuke Sakuma"
    },
    {
      "id": "swsh4.5-70",
      "name": "Poké Kid",
      "set": "swsh4.5",
      "setName": "Shining Fates",
      "number": "70",
      "rarity": "Ultra Rare",
      "image": "https://assets.tcgdex.net/en/swsh/swsh4.5/70",
      "types": null,
      "illustrator": "Sanosuke Sakuma"
    },
    {
      "id": "swsh4.5-SV004",
      "name": "Grookey",
      "set": "swsh4.5",
      "setName": "Shining Fates",
      "number": "SV004",
      "rarity": "Shiny rare",
      "image": "https://assets.tcgdex.net/en/swsh/swsh4.5/SV004",
      "types": [
        "Grass"
      ],
      "illustrator": "Sanosuke Sakuma"
    },
    {
      "id": "swsh4.5-SV047",
      "name": "Galarian Ponyta",
      "set": "swsh4.5",
      "setName": "Shining Fates",
      "number": "SV047",
      "rarity": "Shiny rare",
      "image": "https://assets.tcgdex.net/en/swsh/swsh4.5/SV047",
      "types": [
        "Psychic"
      ],
      "illustrator": "Sanosuke Sakuma"
    },
    {
      "id": "swsh4.5-SV053",
      "name": "Polteageist",
      "set": "swsh4.5",
      "setName": "Shining Fates",
      "number": "SV053",
      "rarity": "Shiny rare",
      "image": "https://assets.tcgdex.net/en/swsh/swsh4.5/SV053",
      "types": [
        "Psychic"
      ],
      "illustrator": "Sanosuke Sakuma"
    },
    {
      "id": "swsh4-119",
      "name": "Jirachi",
      "set": "swsh4",
      "setName": "Vivid Voltage",
      "number": "119",
      "rarity": "Amazing Rare",
      "image": "https://assets.tcgdex.net/en/swsh/swsh4/119",
      "types": [
        "Metal"
      ],
      "illustrator": "Sanosuke Sakuma"
    },
    {
      "id": "swsh4-179",
      "name": "Allister",
      "set": "swsh4",
      "setName": "Vivid Voltage",
      "number": "179",
      "rarity": "Ultra Rare",
      "image": "https://assets.tcgdex.net/en/swsh/swsh4/179",
      "types": null,
      "illustrator": "Sanosuke Sakuma"
    },
    {
      "id": "swsh4-185",
      "name": "Pokémon Center Lady",
      "set": "swsh4",
      "setName": "Vivid Voltage",
      "number": "185",
      "rarity": "Ultra Rare",
      "image": "https://assets.tcgdex.net/en/swsh/swsh4/185",
      "types": null,
      "illustrator": "Sanosuke Sakuma"
    },
    {
      "id": "swsh4-192",
      "name": "Allister",
      "set": "swsh4",
      "setName": "Vivid Voltage",
      "number": "192",
      "rarity": "Secret Rare",
      "image": "https://assets.tcgdex.net/en/swsh/swsh4/192",
      "types": null,
      "illustrator": "Sanosuke Sakuma"
    },
    {
      "id": "swsh4-40",
      "name": "Cramorant",
      "set": "swsh4",
      "setName": "Vivid Voltage",
      "number": "40",
      "rarity": "Uncommon",
      "image": "https://assets.tcgdex.net/en/swsh/swsh4/40",
      "types": [
        "Water"
      ],
      "illustrator": "Sanosuke Sakuma"
    },
    {
      "id": "swsh4-79",
      "name": "Diancie",
      "set": "swsh4",
      "setName": "Vivid Voltage",
      "number": "79",
      "rarity": "Holo Rare",
      "image": "https://assets.tcgdex.net/en/swsh/swsh4/79",
      "types": [
        "Psychic"
      ],
      "illustrator": "Sanosuke Sakuma"
    },
    {
      "id": "swsh4-88",
      "name": "Hitmontop",
      "set": "swsh4",
      "setName": "Vivid Voltage",
      "number": "88",
      "rarity": "Uncommon",
      "image": "https://assets.tcgdex.net/en/swsh/swsh4/88",
      "types": [
        "Fighting"
      ],
      "illustrator": "Sanosuke Sakuma"
    },
    {
      "id": "swsh5-95",
      "name": "Houndour",
      "set": "swsh5",
      "setName": "Battle Styles",
      "number": "95",
      "rarity": "Common",
      "image": "https://assets.tcgdex.net/en/swsh/swsh5/95",
      "types": [
        "Darkness"
      ],
      "illustrator": "Sanosuke Sakuma"
    },
    {
      "id": "swsh6-1",
      "name": "Weedle",
      "set": "swsh6",
      "setName": "Chilling Reign",
      "number": "1",
      "rarity": "Common",
      "image": "https://assets.tcgdex.net/en/swsh/swsh6/1",
      "types": [
        "Grass"
      ],
      "illustrator": "Sanosuke Sakuma"
    },
    {
      "id": "swsh6-132",
      "name": "Caitlin",
      "set": "swsh6",
      "setName": "Chilling Reign",
      "number": "132",
      "rarity": "Uncommon",
      "image": "https://assets.tcgdex.net/en/swsh/swsh6/132",
      "types": null,
      "illustrator": "Sanosuke Sakuma"
    },
    {
      "id": "swsh6-188",
      "name": "Brawly",
      "set": "swsh6",
      "setName": "Chilling Reign",
      "number": "188",
      "rarity": "Ultra Rare",
      "image": "https://assets.tcgdex.net/en/swsh/swsh6/188",
      "types": null,
      "illustrator": "Sanosuke Sakuma"
    },
    {
      "id": "swsh6-190",
      "name": "Doctor",
      "set": "swsh6",
      "setName": "Chilling Reign",
      "number": "190",
      "rarity": "Ultra Rare",
      "image": "https://assets.tcgdex.net/en/swsh/swsh6/190",
      "types": null,
      "illustrator": "Sanosuke Sakuma"
    },
    {
      "id": "swsh6-212",
      "name": "Brawly",
      "set": "swsh6",
      "setName": "Chilling Reign",
      "number": "212",
      "rarity": "Secret Rare",
      "image": "https://assets.tcgdex.net/en/swsh/swsh6/212",
      "types": null,
      "illustrator": "Sanosuke Sakuma"
    },
    {
      "id": "swsh6-214",
      "name": "Doctor",
      "set": "swsh6",
      "setName": "Chilling Reign",
      "number": "214",
      "rarity": "Secret Rare",
      "image": "https://assets.tcgdex.net/en/swsh/swsh6/214",
      "types": null,
      "illustrator": "Sanosuke Sakuma"
    },
    {
      "id": "swsh6-69",
      "name": "Inkay",
      "set": "swsh6",
      "setName": "Chilling Reign",
      "number": "69",
      "rarity": "Common",
      "image": "https://assets.tcgdex.net/en/swsh/swsh6/69",
      "types": [
        "Psychic"
      ],
      "illustrator": "Sanosuke Sakuma"
    },
    {
      "id": "swsh7-143",
      "name": "Copycat",
      "set": "swsh7",
      "setName": "Evolving Skies",
      "number": "143",
      "rarity": "Uncommon",
      "image": "https://assets.tcgdex.net/en/swsh/swsh7/143",
      "types": null,
      "illustrator": "Sanosuke Sakuma"
    },
    {
      "id": "swsh7-200",
      "name": "Copycat",
      "set": "swsh7",
      "setName": "Evolving Skies",
      "number": "200",
      "rarity": "Ultra Rare",
      "image": "https://assets.tcgdex.net/en/swsh/swsh7/200",
      "types": null,
      "illustrator": "Sanosuke Sakuma"
    },
    {
      "id": "swsh7-222",
      "name": "Copycat",
      "set": "swsh7",
      "setName": "Evolving Skies",
      "number": "222",
      "rarity": "Secret Rare",
      "image": "https://assets.tcgdex.net/en/swsh/swsh7/222",
      "types": null,
      "illustrator": "Sanosuke Sakuma"
    },
    {
      "id": "swsh8-109",
      "name": "Morpeko",
      "set": "swsh8",
      "setName": "Fusion Strike",
      "number": "109",
      "rarity": "Common",
      "image": "https://assets.tcgdex.net/en/swsh/swsh8/109",
      "types": [
        "Lightning"
      ],
      "illustrator": "Sanosuke Sakuma"
    },
    {
      "id": "swsh8-228",
      "name": "Cook",
      "set": "swsh8",
      "setName": "Fusion Strike",
      "number": "228",
      "rarity": "Uncommon",
      "image": "https://assets.tcgdex.net/en/swsh/swsh8/228",
      "types": null,
      "illustrator": "Sanosuke Sakuma"
    },
    {
      "id": "swsh8-232",
      "name": "Dancer",
      "set": "swsh8",
      "setName": "Fusion Strike",
      "number": "232",
      "rarity": "Uncommon",
      "image": "https://assets.tcgdex.net/en/swsh/swsh8/232",
      "types": null,
      "illustrator": "Sanosuke Sakuma"
    },
    {
      "id": "swsh8-258",
      "name": "Chili & Cilan & Cress",
      "set": "swsh8",
      "setName": "Fusion Strike",
      "number": "258",
      "rarity": "Ultra Rare",
      "image": "https://assets.tcgdex.net/en/swsh/swsh8/258",
      "types": null,
      "illustrator": "Sanosuke Sakuma"
    },
    {
      "id": "swsh8-273",
      "name": "Chili & Cilan & Cress",
      "set": "swsh8",
      "setName": "Fusion Strike",
      "number": "273",
      "rarity": "Secret Rare",
      "image": "https://assets.tcgdex.net/en/swsh/swsh8/273",
      "types": null,
      "illustrator": "Sanosuke Sakuma"
    },
    {
      "id": "swsh8-59",
      "name": "Azumarill",
      "set": "swsh8",
      "setName": "Fusion Strike",
      "number": "59",
      "rarity": "Rare",
      "image": "https://assets.tcgdex.net/en/swsh/swsh8/59",
      "types": [
        "Water"
      ],
      "illustrator": "Sanosuke Sakuma"
    },
    {
      "id": "swshp-SWSH120",
      "name": "Marnie",
      "set": "swshp",
      "setName": "SWSH Black Star Promos",
      "number": "SWSH120",
      "rarity": "None",
      "image": "https://assets.tcgdex.net/en/swsh/swshp/SWSH120",
      "types": null,
      "illustrator": "Sanosuke Sakuma"
    },
    {
      "id": "xy10-31",
      "name": "Grumpig",
      "set": "xy10",
      "setName": "Fates Collide",
      "number": "31",
      "rarity": "Rare",
      "image": "https://assets.tcgdex.net/en/xy/xy10/31",
      "types": [
        "Psychic"
      ],
      "illustrator": "Sanosuke Sakuma"
    },
    {
      "id": "xy11-28",
      "name": "Shellos",
      "set": "xy11",
      "setName": "Steam Siege",
      "number": "28",
      "rarity": "Common",
      "image": "https://assets.tcgdex.net/en/xy/xy11/28",
      "types": [
        "Water"
      ],
      "illustrator": "Sanosuke Sakuma"
    },
    {
      "id": "xy11-77",
      "name": "Azumarill",
      "set": "xy11",
      "setName": "Steam Siege",
      "number": "77",
      "rarity": "Uncommon",
      "image": "https://assets.tcgdex.net/en/xy/xy11/77",
      "types": [
        "Fairy",
        "Water"
      ],
      "illustrator": "Sanosuke Sakuma"
    },
    {
      "id": "xy1-88",
      "name": "Jigglypuff",
      "set": "xy1",
      "setName": "XY",
      "number": "88",
      "rarity": "Common",
      "image": "https://assets.tcgdex.net/en/xy/xy1/88",
      "types": [
        "Fairy"
      ],
      "illustrator": "Sanosuke Sakuma"
    },
    {
      "id": "xy2-32",
      "name": "Shinx",
      "set": "xy2",
      "setName": "Flashfire",
      "number": "32",
      "rarity": "Common",
      "image": "https://assets.tcgdex.net/en/xy/xy2/32",
      "types": [
        "Lightning"
      ],
      "illustrator": "Sanosuke Sakuma"
    },
    {
      "id": "xy2-85",
      "name": "Lopunny",
      "set": "xy2",
      "setName": "Flashfire",
      "number": "85",
      "rarity": "Rare",
      "image": "https://assets.tcgdex.net/en/xy/xy2/85",
      "types": [
        "Colorless"
      ],
      "illustrator": "Sanosuke Sakuma"
    },
    {
      "id": "xy3-12",
      "name": "Torchic",
      "set": "xy3",
      "setName": "Furious Fists",
      "number": "12",
      "rarity": "Common",
      "image": "https://assets.tcgdex.net/en/xy/xy3/12",
      "types": [
        "Fire"
      ],
      "illustrator": "Sanosuke Sakuma"
    },
    {
      "id": "xy3-27",
      "name": "Pikachu",
      "set": "xy3",
      "setName": "Furious Fists",
      "number": "27",
      "rarity": "Common",
      "image": "https://assets.tcgdex.net/en/xy/xy3/27",
      "types": [
        "Lightning"
      ],
      "illustrator": "Sanosuke Sakuma"
    },
    {
      "id": "xy3-28",
      "name": "Raichu",
      "set": "xy3",
      "setName": "Furious Fists",
      "number": "28",
      "rarity": "Uncommon",
      "image": "https://assets.tcgdex.net/en/xy/xy3/28",
      "types": [
        "Lightning"
      ],
      "illustrator": "Sanosuke Sakuma"
    },
    {
      "id": "xy3-3",
      "name": "Victreebel",
      "set": "xy3",
      "setName": "Furious Fists",
      "number": "3",
      "rarity": "Rare",
      "image": "https://assets.tcgdex.net/en/xy/xy3/3",
      "types": [
        "Grass"
      ],
      "illustrator": "Sanosuke Sakuma"
    },
    {
      "id": "xy4-46",
      "name": "Gligar",
      "set": "xy4",
      "setName": "Phantom Forces",
      "number": "46",
      "rarity": "Common",
      "image": "https://assets.tcgdex.net/en/xy/xy4/46",
      "types": [
        "Fighting"
      ],
      "illustrator": "Sanosuke Sakuma"
    },
    {
      "id": "xy4-54",
      "name": "Mightyena",
      "set": "xy4",
      "setName": "Phantom Forces",
      "number": "54",
      "rarity": "Rare",
      "image": "https://assets.tcgdex.net/en/xy/xy4/54",
      "types": [
        "Darkness"
      ],
      "illustrator": "Sanosuke Sakuma"
    },
    {
      "id": "xy4-59",
      "name": "Skarmory",
      "set": "xy4",
      "setName": "Phantom Forces",
      "number": "59",
      "rarity": "Common",
      "image": "https://assets.tcgdex.net/en/xy/xy4/59",
      "types": [
        "Metal"
      ],
      "illustrator": "Sanosuke Sakuma"
    },
    {
      "id": "xy4-75",
      "name": "Goomy",
      "set": "xy4",
      "setName": "Phantom Forces",
      "number": "75",
      "rarity": "Common",
      "image": "https://assets.tcgdex.net/en/xy/xy4/75",
      "types": [
        "Dragon"
      ],
      "illustrator": "Sanosuke Sakuma"
    },
    {
      "id": "xy4-8",
      "name": "Karrablast",
      "set": "xy4",
      "setName": "Phantom Forces",
      "number": "8",
      "rarity": "Common",
      "image": "https://assets.tcgdex.net/en/xy/xy4/8",
      "types": [
        "Grass"
      ],
      "illustrator": "Sanosuke Sakuma"
    },
    {
      "id": "xy5-31",
      "name": "Seadra",
      "set": "xy5",
      "setName": "Primal Clash",
      "number": "31",
      "rarity": "Uncommon",
      "image": "https://assets.tcgdex.net/en/xy/xy5/31",
      "types": [
        "Water"
      ],
      "illustrator": "Sanosuke Sakuma"
    },
    {
      "id": "xy5-44",
      "name": "Milotic",
      "set": "xy5",
      "setName": "Primal Clash",
      "number": "44",
      "rarity": "Rare",
      "image": "https://assets.tcgdex.net/en/xy/xy5/44",
      "types": [
        "Water"
      ],
      "illustrator": "Sanosuke Sakuma"
    },
    {
      "id": "xy5-60",
      "name": "Electrike",
      "set": "xy5",
      "setName": "Primal Clash",
      "number": "60",
      "rarity": "Uncommon",
      "image": "https://assets.tcgdex.net/en/xy/xy5/60",
      "types": [
        "Lightning"
      ],
      "illustrator": "Sanosuke Sakuma"
    },
    {
      "id": "xy6-42",
      "name": "Jirachi",
      "set": "xy6",
      "setName": "Roaring Skies",
      "number": "42",
      "rarity": "Rare",
      "image": "https://assets.tcgdex.net/en/xy/xy6/42",
      "types": [
        "Metal"
      ],
      "illustrator": "Sanosuke Sakuma"
    },
    {
      "id": "xy6-71",
      "name": "Swellow",
      "set": "xy6",
      "setName": "Roaring Skies",
      "number": "71",
      "rarity": "Rare",
      "image": "https://assets.tcgdex.net/en/xy/xy6/71",
      "types": [
        "Colorless"
      ],
      "illustrator": "Sanosuke Sakuma"
    },
    {
      "id": "xy7-26",
      "name": "Jolteon",
      "set": "xy7",
      "setName": "Ancient Origins",
      "number": "26",
      "rarity": "Rare",
      "image": "https://assets.tcgdex.net/en/xy/xy7/26",
      "types": [
        "Lightning"
      ],
      "illustrator": "Sanosuke Sakuma"
    },
    {
      "id": "xy7-34",
      "name": "Golett",
      "set": "xy7",
      "setName": "Ancient Origins",
      "number": "34",
      "rarity": "Common",
      "image": "https://assets.tcgdex.net/en/xy/xy7/34",
      "types": [
        "Psychic"
      ],
      "illustrator": "Sanosuke Sakuma"
    },
    {
      "id": "xy8-69",
      "name": "Kirlia",
      "set": "xy8",
      "setName": "BREAKthrough",
      "number": "69",
      "rarity": "Uncommon",
      "image": "https://assets.tcgdex.net/en/xy/xy8/69",
      "types": [
        "Psychic"
      ],
      "illustrator": "Sanosuke Sakuma"
    },
    {
      "id": "xy9-38",
      "name": "Froakie",
      "set": "xy9",
      "setName": "BREAKpoint",
      "number": "38",
      "rarity": "Common",
      "image": "https://assets.tcgdex.net/en/xy/xy9/38",
      "types": [
        "Water"
      ],
      "illustrator": "Sanosuke Sakuma"
    },
    {
      "id": "xy9-45",
      "name": "Luxio",
      "set": "xy9",
      "setName": "BREAKpoint",
      "number": "45",
      "rarity": "Uncommon",
      "image": "https://assets.tcgdex.net/en/xy/xy9/45",
      "types": [
        "Lightning"
      ],
      "illustrator": "Sanosuke Sakuma"
    },
    {
      "id": "xy9-82",
      "name": "Clefable",
      "set": "xy9",
      "setName": "BREAKpoint",
      "number": "82",
      "rarity": "Rare",
      "image": "https://assets.tcgdex.net/en/xy/xy9/82",
      "types": [
        "Fairy"
      ],
      "illustrator": "Sanosuke Sakuma"
    },
    {
      "id": "xyp-XY138",
      "name": "Froakie",
      "set": "xyp",
      "setName": "XY Black Star Promos",
      "number": "XY138",
      "rarity": "None",
      "image": "https://assets.tcgdex.net/en/xy/xyp/XY138",
      "types": [
        "Water"
      ],
      "illustrator": "Sanosuke Sakuma"
    },
    {
      "id": "xyp-XY162",
      "name": "Greninja",
      "set": "xyp",
      "setName": "XY Black Star Promos",
      "number": "XY162",
      "rarity": "Common",
      "image": "https://assets.tcgdex.net/en/xy/xyp/XY162",
      "types": [
        "Water"
      ],
      "illustrator": "Sanosuke Sakuma"
    },
    {
      "id": "xyp-XY22",
      "name": "Darkrai",
      "set": "xyp",
      "setName": "XY Black Star Promos",
      "number": "XY22",
      "rarity": "None",
      "image": "https://assets.tcgdex.net/en/xy/xyp/XY22",
      "types": [
        "Darkness"
      ],
      "illustrator": "Sanosuke Sakuma"
    },
    {
      "id": "xyp-XY23",
      "name": "Shiftry",
      "set": "xyp",
      "setName": "XY Black Star Promos",
      "number": "XY23",
      "rarity": "None",
      "image": "https://assets.tcgdex.net/en/xy/xyp/XY23",
      "types": [
        "Grass"
      ],
      "illustrator": "Sanosuke Sakuma"
    },
    {
      "id": "xyp-XY78",
      "name": "Latias",
      "set": "xyp",
      "setName": "XY Black Star Promos",
      "number": "XY78",
      "rarity": "None",
      "image": "https://assets.tcgdex.net/en/xy/xyp/XY78",
      "types": [
        "Dragon"
      ],
      "illustrator": "Sanosuke Sakuma"
    }
  ]
}