{
  "name": "Krgc",
  "totalCards": 23,
  "cards": [
    {
      "id": "A2-062",
      "name": "Rotom",
      "set": "A2",
      "setName": "Space-Time Smackdown",
      "number": "062",
      "rarity": "One Diamond",
      "image": "https://assets.tcgdex.net/en/tcgp/A2/062",
      "types": [
        "Lightning"
      ],
      "illustrator": "Krgc"
    },
    {
      "id": "A2b-050",
      "name": "Shroodle",
      "set": "A2b",
      "setName": "Shining Revelry",
      "number": "050",
      "rarity": "One Diamond",
      "image": "https://assets.tcgdex.net/en/tcgp/A2b/050",
      "types": [
        "Darkness"
      ],
      "illustrator": "Krgc"
    },
    {
      "id": "A2b-051",
      "name": "Grafaiai",
      "set": "A2b",
      "setName": "Shining Revelry",
      "number": "051",
      "rarity": "Three Diamond",
      "image": "https://assets.tcgdex.net/en/tcgp/A2b/051",
      "types": [
        "Darkness"
      ],
      "illustrator": "Krgc"
    },
    {
      "id": "B1-272",
      "name": "Mega Pinsir ex",
      "set": "B1",
      "setName": "Mega Rising",
      "number": "272",
      "rarity": "Two Star",
      "image": "https://assets.tcgdex.net/en/tcgp/B1/272",
      "types": [
        "Grass"
      ],
      "illustrator": "Krgc"
    },
    {
      "id": "B1a-022",
      "name": "Clauncher",
      "set": "B1a",
      "setName": "Crimson Blaze",
      "number": "022",
      "rarity": "One Diamond",
      "image": "https://assets.tcgdex.net/en/tcgp/B1a/022",
      "types": [
        "Water"
      ],
      "illustrator": "Krgc"
    },
    {
      "id": "B2-220",
      "name": "Kabuto",
      "set": "B2",
      "setName": "Fantastical Parade",
      "number": "220",
      "rarity": "One Shiny",
      "image": "https://assets.tcgdex.net/en/tcgp/B2/220",
      "types": [
        "Fighting"
      ],
      "illustrator": "Krgc"
    },
    {
      "id": "B2-221",
      "name": "Kabutops",
      "set": "B2",
      "setName": "Fantastical Parade",
      "number": "221",
      "rarity": "One Shiny",
      "image": "https://assets.tcgdex.net/en/tcgp/B2/221",
      "types": [
        "Fighting"
      ],
      "illustrator": "Krgc"
    },
    {
      "id": "me01-045",
      "name": "Magnemite",
      "set": "me01",
      "setName": "Mega Evolution",
      "number": "045",
      "rarity": "Common",
      "image": "https://assets.tcgdex.net/en/me/me01/045",
      "types": [
        "Lightning"
      ],
      "illustrator": "Krgc"
    },
    {
      "id": "me02.5-044",
      "name": "Sneasel",
      "set": "me02.5",
      "setName": "Ascended Heroes",
      "number": "044",
      "rarity": "Common",
      "image": "https://assets.tcgdex.net/en/me/me02.5/044",
      "types": [
        "Water"
      ],
      "illustrator": "Krgc"
    },
    {
      "id": "me02.5-245",
      "name": "Galarian Obstagoon",
      "set": "me02.5",
      "setName": "Ascended Heroes",
      "number": "245",
      "rarity": "Illustration rare",
      "image": "https://assets.tcgdex.net/en/me/me02.5/245",
      "types": [
        "Darkness"
      ],
      "illustrator": "Krgc"
    },
    {
      "id": "mep-017",
      "name": "Toxtricity",
      "set": "mep",
      "setName": "MEP Black Star Promos",
      "number": "017",
      "rarity": "Rare",
      "image": null,
      "types": [
        "Darkness"
      ],
      "illustrator": "Krgc"
    },
    {
      "id": "P-A-010",
      "name": "Mewtwo",
      "set": "P-A",
      "setName": "Promos-A",
      "number": "010",
      "rarity": "None",
      "image": "https://assets.tcgdex.net/en/tcgp/P-A/010",
      "types": [
        "Psychic"
      ],
      "illustrator": "Krgc"
    },
    {
      "id": "P-A-056",
      "name": "Ekans",
      "set": "P-A",
      "setName": "Promos-A",
      "number": "056",
      "rarity": "None",
      "image": "https://assets.tcgdex.net/en/tcgp/P-A/056",
      "types": [
        "Darkness"
      ],
      "illustrator": "Krgc"
    },
    {
      "id": "sv05-037",
      "name": "Centiskorch",
      "set": "sv05",
      "setName": "Temporal Forces",
      "number": "037",
      "rarity": "Uncommon",
      "image": "https://assets.tcgdex.net/en/sv/sv05/037",
      "types": [
        "Fire"
      ],
      "illustrator": "Krgc"
    },
    {
      "id": "sv06.5-013",
      "name": "Sneasel",
      "set": "sv06.5",
      "setName": "Shrouded Fable",
      "number": "013",
      "rarity": "Common",
      "image": "https://assets.tcgdex.net/en/sv/sv06.5/013",
      "types": [
        "Water"
      ],
      "illustrator": "Krgc"
    },
    {
      "id": "sv06-116",
      "name": "Whirlipede",
      "set": "sv06",
      "setName": "Twilight Masquerade",
      "number": "116",
      "rarity": "Common",
      "image": "https://assets.tcgdex.net/en/sv/sv06/116",
      "types": [
        "Darkness"
      ],
      "illustrator": "Krgc"
    },
    {
      "id": "sv06-173",
      "name": "Infernape",
      "set": "sv06",
      "setName": "Twilight Masquerade",
      "number": "173",
      "rarity": "Illustration rare",
      "image": "https://assets.tcgdex.net/en/sv/sv06/173",
      "types": [
        "Fire"
      ],
      "illustrator": "Krgc"
    },
    {
      "id": "sv07-029",
      "name": "Charcadet",
      "set": "sv07",
      "setName": "Stellar Crown",
      "number": "029",
      "rarity": "Common",
      "image": "https://assets.tcgdex.net/en/sv/sv07/029",
      "types": [
        "Fire"
      ],
      "illustrator": "Krgc"
    },
    {
      "id": "sv10.5w-038",
      "name": "Sigilyph",
      "set": "sv10.5w",
      "setName": "White Flare",
      "number": "038",
      "rarity": "Uncommon",
      "image": "https://assets.tcgdex.net/en/sv/sv10.5w/038",
      "types": [
        "Psychic"
      ],
      "illustrator": "Krgc"
    },
    {
      "id": "sv10.5w-128",
      "name": "Boldore",
      "set": "sv10.5w",
      "setName": "White Flare",
      "number": "128",
      "rarity": "Illustration rare",
      "image": "https://assets.tcgdex.net/en/sv/sv10.5w/128",
      "types": [
        "Fighting"
      ],
      "illustrator": "Krgc"
    },
    {
      "id": "sv10-037",
      "name": "Team Rocket's Houndour",
      "set": "sv10",
      "setName": "Destined Rivals",
      "number": "037",
      "rarity": "Common",
      "image": "https://assets.tcgdex.net/en/sv/sv10/037",
      "types": [
        "Fire"
      ],
      "illustrator": "Krgc"
    },
    {
      "id": "sv10-238",
      "name": "Team Rocket's Giovanni",
      "set": "sv10",
      "setName": "Destined Rivals",
      "number": "238",
      "rarity": "Special illustration rare",
      "image": "https://assets.tcgdex.net/en/sv/sv10/238",
      "types": null,
      "illustrator": "Krgc"
    },
    {
      "id": "svp-201",
      "name": "Zebstrika",
      "set": "svp",
      "setName": "SVP Black Star Promos",
      "number": "201",
      "rarity": "None",
      "image": null,
      "types": [
        "Lightning"
      ],
      "illustrator": "Krgc"
    }
  ]
}