{
  "name": "hechima",
  "totalCards": 2,
  "cards": [
    {
      "id": "A3-155",
      "name": "Lylia",
      "set": "A3",
      "setName": "Guardianes Celestiales",
      "number": "155",
      "rarity": "Dos Diamantes",
      "image": "https://assets.tcgdex.net/es/tcgp/A3/155",
      "types": null,
      "illustrator": "hechima"
    },
    {
      "id": "A3-197",
      "name": "Lylia",
      "set": "A3",
      "setName": "Guardianes Celestiales",
      "number": "197",
      "rarity": "Dos Estrellas",
      "image": "https://assets.tcgdex.net/es/tcgp/A3/197",
      "types": null,
      "illustrator": "hechima"
    }
  ]
}