{
  "name": "Oswaldo KATO",
  "totalCards": 82,
  "cards": [
    {
      "id": "A1-127",
      "name": "Jynx",
      "set": "A1",
      "setName": "Genes Formidables",
      "number": "127",
      "rarity": "Un Diamante",
      "image": "https://assets.tcgdex.net/es/tcgp/A1/127",
      "types": [
        "Psíquico"
      ],
      "illustrator": "Oswaldo KATO"
    },
    {
      "id": "A2-026",
      "name": "Magcargo",
      "set": "A2",
      "setName": "Pugna Espaciotemporal",
      "number": "026",
      "rarity": "Dos Diamantes",
      "image": "https://assets.tcgdex.net/es/tcgp/A2/026",
      "types": [
        "Fuego"
      ],
      "illustrator": "Oswaldo KATO"
    },
    {
      "id": "A2-081",
      "name": "Rhydon",
      "set": "A2",
      "setName": "Pugna Espaciotemporal",
      "number": "081",
      "rarity": "Dos Diamantes",
      "image": "https://assets.tcgdex.net/es/tcgp/A2/081",
      "types": [
        "Lucha"
      ],
      "illustrator": "Oswaldo KATO"
    },
    {
      "id": "A2-111",
      "name": "Skarmory",
      "set": "A2",
      "setName": "Pugna Espaciotemporal",
      "number": "111",
      "rarity": "Dos Diamantes",
      "image": "https://assets.tcgdex.net/es/tcgp/A2/111",
      "types": [
        "Metálica"
      ],
      "illustrator": "Oswaldo KATO"
    },
    {
      "id": "A2-120",
      "name": "Heatran",
      "set": "A2",
      "setName": "Pugna Espaciotemporal",
      "number": "120",
      "rarity": "Tres Diamantes",
      "image": "https://assets.tcgdex.net/es/tcgp/A2/120",
      "types": [
        "Metálica"
      ],
      "illustrator": "Oswaldo KATO"
    },
    {
      "id": "A2-202",
      "name": "Darkrai ex",
      "set": "A2",
      "setName": "Pugna Espaciotemporal",
      "number": "202",
      "rarity": "Dos Estrellas",
      "image": "https://assets.tcgdex.net/es/tcgp/A2/202",
      "types": [
        "Oscura"
      ],
      "illustrator": "Oswaldo KATO"
    },
    {
      "id": "A3-098",
      "name": "Rockruff",
      "set": "A3",
      "setName": "Guardianes Celestiales",
      "number": "098",
      "rarity": "Un Diamante",
      "image": "https://assets.tcgdex.net/es/tcgp/A3/098",
      "types": [
        "Lucha"
      ],
      "illustrator": "Oswaldo KATO"
    },
    {
      "id": "A3-099",
      "name": "Rockruff",
      "set": "A3",
      "setName": "Guardianes Celestiales",
      "number": "099",
      "rarity": "Un Diamante",
      "image": "https://assets.tcgdex.net/es/tcgp/A3/099",
      "types": [
        "Lucha"
      ],
      "illustrator": "Oswaldo KATO"
    },
    {
      "id": "B2a-031",
      "name": "Veluza",
      "set": "B2a",
      "setName": "Paldean Wonders",
      "number": "031",
      "rarity": "Un Diamante",
      "image": null,
      "types": [
        "Agua"
      ],
      "illustrator": "Oswaldo KATO"
    },
    {
      "id": "B2a-036",
      "name": "Baxcalibur",
      "set": "B2a",
      "setName": "Paldean Wonders",
      "number": "036",
      "rarity": "Tres Diamantes",
      "image": null,
      "types": [
        "Agua"
      ],
      "illustrator": "Oswaldo KATO"
    },
    {
      "id": "B2a-049",
      "name": "Rabsca",
      "set": "B2a",
      "setName": "Paldean Wonders",
      "number": "049",
      "rarity": "Dos Diamantes",
      "image": null,
      "types": [
        "Psíquico"
      ],
      "illustrator": "Oswaldo KATO"
    },
    {
      "id": "B2a-059",
      "name": "Toedscool",
      "set": "B2a",
      "setName": "Paldean Wonders",
      "number": "059",
      "rarity": "Un Diamante",
      "image": null,
      "types": [
        "Lucha"
      ],
      "illustrator": "Oswaldo KATO"
    },
    {
      "id": "B2a-083",
      "name": "Squawkabilly",
      "set": "B2a",
      "setName": "Paldean Wonders",
      "number": "083",
      "rarity": "Un Diamante",
      "image": null,
      "types": [
        "Incolora"
      ],
      "illustrator": "Oswaldo KATO"
    },
    {
      "id": "me01-108",
      "name": "Lopunny",
      "set": "me01",
      "setName": "Megaevolución",
      "number": "108",
      "rarity": "Común",
      "image": "https://assets.tcgdex.net/es/me/me01/108",
      "types": [
        "Incolora"
      ],
      "illustrator": "Oswaldo KATO"
    },
    {
      "id": "me04-047",
      "name": "Claydol",
      "set": "me04",
      "setName": "Caos Creciente",
      "number": "047",
      "rarity": "Uncommon",
      "image": "https://assets.tcgdex.net/es/me/me04/047",
      "types": [
        "Lucha"
      ],
      "illustrator": "Oswaldo KATO"
    },
    {
      "id": "mep-016",
      "name": "Flygon",
      "set": "mep",
      "setName": "MEP Black Star Promos",
      "number": "016",
      "rarity": "Ninguno",
      "image": null,
      "types": [
        "Lucha"
      ],
      "illustrator": "Oswaldo KATO"
    },
    {
      "id": "sv01-162",
      "name": "Squawkabilly",
      "set": "sv01",
      "setName": "Escarlata y Púrpura",
      "number": "162",
      "rarity": "Común",
      "image": "https://assets.tcgdex.net/es/sv/sv01/162",
      "types": [
        "Incolora"
      ],
      "illustrator": "Oswaldo KATO"
    },
    {
      "id": "sv01-167",
      "name": "Cancha en la Playa",
      "set": "sv01",
      "setName": "Escarlata y Púrpura",
      "number": "167",
      "rarity": "Uncommon",
      "image": "https://assets.tcgdex.net/es/sv/sv01/167",
      "types": null,
      "illustrator": "Oswaldo KATO"
    },
    {
      "id": "sv01-178",
      "name": "Ciudad Meseta",
      "set": "sv01",
      "setName": "Escarlata y Púrpura",
      "number": "178",
      "rarity": "Uncommon",
      "image": "https://assets.tcgdex.net/es/sv/sv01/178",
      "types": null,
      "illustrator": "Oswaldo KATO"
    },
    {
      "id": "sv01-200",
      "name": "Dolliv",
      "set": "sv01",
      "setName": "Escarlata y Púrpura",
      "number": "200",
      "rarity": "Rara Ilustración",
      "image": "https://assets.tcgdex.net/es/sv/sv01/200",
      "types": [
        "Planta"
      ],
      "illustrator": "Oswaldo KATO"
    },
    {
      "id": "sv01-250",
      "name": "Cinio",
      "set": "sv01",
      "setName": "Escarlata y Púrpura",
      "number": "250",
      "rarity": "Rara Ilustración Especial",
      "image": "https://assets.tcgdex.net/es/sv/sv01/250",
      "types": null,
      "illustrator": "Oswaldo KATO"
    },
    {
      "id": "sv02-018",
      "name": "Spidops",
      "set": "sv02",
      "setName": "Evoluciones en Paldea",
      "number": "018",
      "rarity": "Uncommon",
      "image": "https://assets.tcgdex.net/es/sv/sv02/018",
      "types": [
        "Planta"
      ],
      "illustrator": "Oswaldo KATO"
    },
    {
      "id": "sv02-041",
      "name": "Tauros de Paldea",
      "set": "sv02",
      "setName": "Evoluciones en Paldea",
      "number": "041",
      "rarity": "Uncommon",
      "image": "https://assets.tcgdex.net/es/sv/sv02/041",
      "types": [
        "Agua"
      ],
      "illustrator": "Oswaldo KATO"
    },
    {
      "id": "sv02-069",
      "name": "Shinx",
      "set": "sv02",
      "setName": "Evoluciones en Paldea",
      "number": "069",
      "rarity": "Común",
      "image": "https://assets.tcgdex.net/es/sv/sv02/069",
      "types": [
        "Rayo"
      ],
      "illustrator": "Oswaldo KATO"
    },
    {
      "id": "sv02-099",
      "name": "Rabsca",
      "set": "sv02",
      "setName": "Evoluciones en Paldea",
      "number": "099",
      "rarity": "Rara",
      "image": "https://assets.tcgdex.net/es/sv/sv02/099",
      "types": [
        "Psíquico"
      ],
      "illustrator": "Oswaldo KATO"
    },
    {
      "id": "sv02-149",
      "name": "Cufant",
      "set": "sv02",
      "setName": "Evoluciones en Paldea",
      "number": "149",
      "rarity": "Común",
      "image": "https://assets.tcgdex.net/es/sv/sv02/149",
      "types": [
        "Metálica"
      ],
      "illustrator": "Oswaldo KATO"
    },
    {
      "id": "sv02-166",
      "name": "Tandemaus",
      "set": "sv02",
      "setName": "Evoluciones en Paldea",
      "number": "166",
      "rarity": "Común",
      "image": "https://assets.tcgdex.net/es/sv/sv02/166",
      "types": [
        "Incolora"
      ],
      "illustrator": "Oswaldo KATO"
    },
    {
      "id": "sv02-171",
      "name": "Pueblo Altamía",
      "set": "sv02",
      "setName": "Evoluciones en Paldea",
      "number": "171",
      "rarity": "Uncommon",
      "image": "https://assets.tcgdex.net/es/sv/sv02/171",
      "types": null,
      "illustrator": "Oswaldo KATO"
    },
    {
      "id": "sv02-223",
      "name": "Grafaiai",
      "set": "sv02",
      "setName": "Evoluciones en Paldea",
      "number": "223",
      "rarity": "Rara Ilustración",
      "image": "https://assets.tcgdex.net/es/sv/sv02/223",
      "types": [
        "Oscura"
      ],
      "illustrator": "Oswaldo KATO"
    },
    {
      "id": "sv03.5-016",
      "name": "Pidgey",
      "set": "sv03.5",
      "setName": "151",
      "number": "016",
      "rarity": "Común",
      "image": "https://assets.tcgdex.net/es/sv/sv03.5/016",
      "types": [
        "Incolora"
      ],
      "illustrator": "Oswaldo KATO"
    },
    {
      "id": "sv03.5-017",
      "name": "Pidgeotto",
      "set": "sv03.5",
      "setName": "151",
      "number": "017",
      "rarity": "Común",
      "image": "https://assets.tcgdex.net/es/sv/sv03.5/017",
      "types": [
        "Incolora"
      ],
      "illustrator": "Oswaldo KATO"
    },
    {
      "id": "sv03.5-018",
      "name": "Pidgeot",
      "set": "sv03.5",
      "setName": "151",
      "number": "018",
      "rarity": "Uncommon",
      "image": "https://assets.tcgdex.net/es/sv/sv03.5/018",
      "types": [
        "Incolora"
      ],
      "illustrator": "Oswaldo KATO"
    },
    {
      "id": "sv03.5-157",
      "name": "Camino de Bicis",
      "set": "sv03.5",
      "setName": "151",
      "number": "157",
      "rarity": "Uncommon",
      "image": "https://assets.tcgdex.net/es/sv/sv03.5/157",
      "types": null,
      "illustrator": "Oswaldo KATO"
    },
    {
      "id": "sv03.5-178",
      "name": "Tangela",
      "set": "sv03.5",
      "setName": "151",
      "number": "178",
      "rarity": "Rara Ilustración",
      "image": "https://assets.tcgdex.net/es/sv/sv03.5/178",
      "types": [
        "Planta"
      ],
      "illustrator": "Oswaldo KATO"
    },
    {
      "id": "sv03-118",
      "name": "Toedscool",
      "set": "sv03",
      "setName": "Llamas Obsidianas",
      "number": "118",
      "rarity": "Común",
      "image": "https://assets.tcgdex.net/es/sv/sv03/118",
      "types": [
        "Lucha"
      ],
      "illustrator": "Oswaldo KATO"
    },
    {
      "id": "sv03-169",
      "name": "Swablu",
      "set": "sv03",
      "setName": "Llamas Obsidianas",
      "number": "169",
      "rarity": "Común",
      "image": "https://assets.tcgdex.net/es/sv/sv03/169",
      "types": [
        "Incolora"
      ],
      "illustrator": "Oswaldo KATO"
    },
    {
      "id": "sv03-192",
      "name": "Sede de la Liga Pokémon",
      "set": "sv03",
      "setName": "Llamas Obsidianas",
      "number": "192",
      "rarity": "Uncommon",
      "image": "https://assets.tcgdex.net/es/sv/sv03/192",
      "types": null,
      "illustrator": "Oswaldo KATO"
    },
    {
      "id": "sv03-196",
      "name": "Tienda Local",
      "set": "sv03",
      "setName": "Llamas Obsidianas",
      "number": "196",
      "rarity": "Común",
      "image": "https://assets.tcgdex.net/es/sv/sv03/196",
      "types": null,
      "illustrator": "Oswaldo KATO"
    },
    {
      "id": "sv03-229",
      "name": "Pueblo Altamía",
      "set": "sv03",
      "setName": "Llamas Obsidianas",
      "number": "229",
      "rarity": "Rara Híper",
      "image": "https://assets.tcgdex.net/es/sv/sv03/229",
      "types": null,
      "illustrator": "Oswaldo KATO"
    },
    {
      "id": "sv04.5-073",
      "name": "Tandemaus",
      "set": "sv04.5",
      "setName": "Destinos de Paldea",
      "number": "073",
      "rarity": "Común",
      "image": "https://assets.tcgdex.net/es/sv/sv04.5/073",
      "types": [
        "Incolora"
      ],
      "illustrator": "Oswaldo KATO"
    },
    {
      "id": "sv04.5-076",
      "name": "Pueblo Altamía",
      "set": "sv04.5",
      "setName": "Destinos de Paldea",
      "number": "076",
      "rarity": "Uncommon",
      "image": "https://assets.tcgdex.net/es/sv/sv04.5/076",
      "types": null,
      "illustrator": "Oswaldo KATO"
    },
    {
      "id": "sv04-029",
      "name": "Chi-Yu",
      "set": "sv04",
      "setName": "Brecha Paradójica",
      "number": "029",
      "rarity": "Rara",
      "image": "https://assets.tcgdex.net/es/sv/sv04/029",
      "types": [
        "Fuego"
      ],
      "illustrator": "Oswaldo KATO"
    },
    {
      "id": "sv04-054",
      "name": "Veluza",
      "set": "sv04",
      "setName": "Brecha Paradójica",
      "number": "054",
      "rarity": "Uncommon",
      "image": "https://assets.tcgdex.net/es/sv/sv04/054",
      "types": [
        "Agua"
      ],
      "illustrator": "Oswaldo KATO"
    },
    {
      "id": "sv04-056",
      "name": "Ferrosaco",
      "set": "sv04",
      "setName": "Brecha Paradójica",
      "number": "056",
      "rarity": "Uncommon",
      "image": "https://assets.tcgdex.net/es/sv/sv04/056",
      "types": [
        "Agua"
      ],
      "illustrator": "Oswaldo KATO"
    },
    {
      "id": "sv04-083",
      "name": "Tinkatink",
      "set": "sv04",
      "setName": "Brecha Paradójica",
      "number": "083",
      "rarity": "Común",
      "image": "https://assets.tcgdex.net/es/sv/sv04/083",
      "types": [
        "Psíquico"
      ],
      "illustrator": "Oswaldo KATO"
    },
    {
      "id": "sv04-245",
      "name": "Garchomp ex",
      "set": "sv04",
      "setName": "Brecha Paradójica",
      "number": "245",
      "rarity": "Rara Ilustración Especial",
      "image": "https://assets.tcgdex.net/es/sv/sv04/245",
      "types": [
        "Agua"
      ],
      "illustrator": "Oswaldo KATO"
    },
    {
      "id": "sv04-263",
      "name": "Cancha en la Playa",
      "set": "sv04",
      "setName": "Brecha Paradójica",
      "number": "263",
      "rarity": "Rara Híper",
      "image": "https://assets.tcgdex.net/es/sv/sv04/263",
      "types": null,
      "illustrator": "Oswaldo KATO"
    },
    {
      "id": "sv05-059",
      "name": "Boltund",
      "set": "sv05",
      "setName": "Fuerzas Temporales",
      "number": "059",
      "rarity": "Uncommon",
      "image": "https://assets.tcgdex.net/es/sv/sv05/059",
      "types": [
        "Rayo"
      ],
      "illustrator": "Oswaldo KATO"
    },
    {
      "id": "sv05-117",
      "name": "Melmetal",
      "set": "sv05",
      "setName": "Fuerzas Temporales",
      "number": "117",
      "rarity": "Rara",
      "image": "https://assets.tcgdex.net/es/sv/sv05/117",
      "types": [
        "Metálica"
      ],
      "illustrator": "Oswaldo KATO"
    },
    {
      "id": "sv05-164",
      "name": "Grotle",
      "set": "sv05",
      "setName": "Fuerzas Temporales",
      "number": "164",
      "rarity": "Rara Ilustración",
      "image": "https://assets.tcgdex.net/es/sv/sv05/164",
      "types": [
        "Planta"
      ],
      "illustrator": "Oswaldo KATO"
    },
    {
      "id": "sv06-013",
      "name": "Trevenant",
      "set": "sv06",
      "setName": "Mascarada Crepuscular",
      "number": "013",
      "rarity": "Común",
      "image": "https://assets.tcgdex.net/es/sv/sv06/013",
      "types": [
        "Planta"
      ],
      "illustrator": "Oswaldo KATO"
    },
    {
      "id": "sv07-046",
      "name": "Electabuzz",
      "set": "sv07",
      "setName": "Corona Astral",
      "number": "046",
      "rarity": "Común",
      "image": "https://assets.tcgdex.net/es/sv/sv07/046",
      "types": [
        "Rayo"
      ],
      "illustrator": "Oswaldo KATO"
    },
    {
      "id": "sv07-107",
      "name": "Archaludon",
      "set": "sv07",
      "setName": "Corona Astral",
      "number": "107",
      "rarity": "Rara",
      "image": "https://assets.tcgdex.net/es/sv/sv07/107",
      "types": [
        "Metálica"
      ],
      "illustrator": "Oswaldo KATO"
    },
    {
      "id": "sv08.5-019",
      "name": "Slowking",
      "set": "sv08.5",
      "setName": "Evoluciones Prismáticas",
      "number": "019",
      "rarity": "Uncommon",
      "image": "https://assets.tcgdex.net/es/sv/sv08.5/019",
      "types": [
        "Agua"
      ],
      "illustrator": "Oswaldo KATO"
    },
    {
      "id": "sv08.5-070",
      "name": "Archaludon",
      "set": "sv08.5",
      "setName": "Evoluciones Prismáticas",
      "number": "070",
      "rarity": "Rara",
      "image": "https://assets.tcgdex.net/es/sv/sv08.5/070",
      "types": [
        "Metálica"
      ],
      "illustrator": "Oswaldo KATO"
    },
    {
      "id": "sv08-003",
      "name": "Exeggutor",
      "set": "sv08",
      "setName": "Chispas Fulgurantes",
      "number": "003",
      "rarity": "Uncommon",
      "image": "https://assets.tcgdex.net/es/sv/sv08/003",
      "types": [
        "Planta"
      ],
      "illustrator": "Oswaldo KATO"
    },
    {
      "id": "sv08-140",
      "name": "Appletun",
      "set": "sv08",
      "setName": "Chispas Fulgurantes",
      "number": "140",
      "rarity": "Uncommon",
      "image": "https://assets.tcgdex.net/es/sv/sv08/140",
      "types": [
        "Dragón"
      ],
      "illustrator": "Oswaldo KATO"
    },
    {
      "id": "sv09-062",
      "name": "Metang",
      "set": "sv09",
      "setName": "Juntos de Aventuras",
      "number": "062",
      "rarity": "Común",
      "image": "https://assets.tcgdex.net/es/sv/sv09/062",
      "types": [
        "Psíquico"
      ],
      "illustrator": "Oswaldo KATO"
    },
    {
      "id": "sv09-125",
      "name": "Minccino",
      "set": "sv09",
      "setName": "Juntos de Aventuras",
      "number": "125",
      "rarity": "Común",
      "image": "https://assets.tcgdex.net/es/sv/sv09/125",
      "types": [
        "Incolora"
      ],
      "illustrator": "Oswaldo KATO"
    },
    {
      "id": "sv10.5w-001",
      "name": "Sewaddle",
      "set": "sv10.5w",
      "setName": "Llama Blanca",
      "number": "001",
      "rarity": "Común",
      "image": "https://assets.tcgdex.net/es/sv/sv10.5w/001",
      "types": [
        "Planta"
      ],
      "illustrator": "Oswaldo KATO"
    },
    {
      "id": "sv10.5w-002",
      "name": "Swadloon",
      "set": "sv10.5w",
      "setName": "Llama Blanca",
      "number": "002",
      "rarity": "Común",
      "image": "https://assets.tcgdex.net/es/sv/sv10.5w/002",
      "types": [
        "Planta"
      ],
      "illustrator": "Oswaldo KATO"
    },
    {
      "id": "sv10.5w-003",
      "name": "Leavanny",
      "set": "sv10.5w",
      "setName": "Llama Blanca",
      "number": "003",
      "rarity": "Uncommon",
      "image": "https://assets.tcgdex.net/es/sv/sv10.5w/003",
      "types": [
        "Planta"
      ],
      "illustrator": "Oswaldo KATO"
    },
    {
      "id": "sv10.5w-140",
      "name": "Trubbish",
      "set": "sv10.5w",
      "setName": "Llama Blanca",
      "number": "140",
      "rarity": "Rara Ilustración",
      "image": "https://assets.tcgdex.net/es/sv/sv10.5w/140",
      "types": [
        "Oscura"
      ],
      "illustrator": "Oswaldo KATO"
    },
    {
      "id": "sv10-153",
      "name": "Porygon del Team Rocket",
      "set": "sv10",
      "setName": "Rivales Predestinados",
      "number": "153",
      "rarity": "Común",
      "image": "https://assets.tcgdex.net/es/sv/sv10/153",
      "types": [
        "Incolora"
      ],
      "illustrator": "Oswaldo KATO"
    },
    {
      "id": "sv10-158",
      "name": "Skwovet de Damián",
      "set": "sv10",
      "setName": "Rivales Predestinados",
      "number": "158",
      "rarity": "Común",
      "image": "https://assets.tcgdex.net/es/sv/sv10/158",
      "types": [
        "Incolora"
      ],
      "illustrator": "Oswaldo KATO"
    },
    {
      "id": "svp-019",
      "name": "Baxcalibur",
      "set": "svp",
      "setName": "SVP Black Star Promos",
      "number": "019",
      "rarity": "Ninguno",
      "image": "https://assets.tcgdex.net/es/sv/svp/019",
      "types": [
        "Agua"
      ],
      "illustrator": "Oswaldo KATO"
    },
    {
      "id": "swsh6-105",
      "name": "Venipede",
      "set": "swsh6",
      "setName": "Reinado Escalofriante",
      "number": "105",
      "rarity": "Común",
      "image": "https://assets.tcgdex.net/es/swsh/swsh6/105",
      "types": [
        "Oscura"
      ],
      "illustrator": "Oswaldo KATO"
    },
    {
      "id": "swsh6-135",
      "name": "Colina del Maxiárbol",
      "set": "swsh6",
      "setName": "Reinado Escalofriante",
      "number": "135",
      "rarity": "Uncommon",
      "image": "https://assets.tcgdex.net/es/swsh/swsh6/135",
      "types": null,
      "illustrator": "Oswaldo KATO"
    },
    {
      "id": "swsh6-147",
      "name": "Viejo Cementerio",
      "set": "swsh6",
      "setName": "Reinado Escalofriante",
      "number": "147",
      "rarity": "Uncommon",
      "image": "https://assets.tcgdex.net/es/swsh/swsh6/147",
      "types": null,
      "illustrator": "Oswaldo KATO"
    },
    {
      "id": "swsh6-148",
      "name": "Senda Blancacima",
      "set": "swsh6",
      "setName": "Reinado Escalofriante",
      "number": "148",
      "rarity": "Uncommon",
      "image": "https://assets.tcgdex.net/es/swsh/swsh6/148",
      "types": null,
      "illustrator": "Oswaldo KATO"
    },
    {
      "id": "swsh6-203",
      "name": "Calyrex Jinete Glacial VMAX",
      "set": "swsh6",
      "setName": "Reinado Escalofriante",
      "number": "203",
      "rarity": "Rara Secreta",
      "image": "https://assets.tcgdex.net/es/swsh/swsh6/203",
      "types": [
        "Agua"
      ],
      "illustrator": "Oswaldo KATO"
    },
    {
      "id": "swsh7-157",
      "name": "Galería Comercial",
      "set": "swsh7",
      "setName": "Cielos Evolutivos",
      "number": "157",
      "rarity": "Uncommon",
      "image": "https://assets.tcgdex.net/es/swsh/swsh7/157",
      "types": null,
      "illustrator": "Oswaldo KATO"
    },
    {
      "id": "swsh7-182",
      "name": "Golurk V",
      "set": "swsh7",
      "setName": "Cielos Evolutivos",
      "number": "182",
      "rarity": "Ultra Rara",
      "image": "https://assets.tcgdex.net/es/swsh/swsh7/182",
      "types": [
        "Psíquico"
      ],
      "illustrator": "Oswaldo KATO"
    },
    {
      "id": "swsh7-6",
      "name": "Tropius",
      "set": "swsh7",
      "setName": "Cielos Evolutivos",
      "number": "6",
      "rarity": "Rara",
      "image": "https://assets.tcgdex.net/es/swsh/swsh7/6",
      "types": [
        "Planta"
      ],
      "illustrator": "Oswaldo KATO"
    },
    {
      "id": "swsh8-142",
      "name": "Makuhita",
      "set": "swsh8",
      "setName": "Golpe Fusión",
      "number": "142",
      "rarity": "Común",
      "image": "https://assets.tcgdex.net/es/swsh/swsh8/142",
      "types": [
        "Lucha"
      ],
      "illustrator": "Oswaldo KATO"
    },
    {
      "id": "swsh8-187",
      "name": "Togedemaru",
      "set": "swsh8",
      "setName": "Golpe Fusión",
      "number": "187",
      "rarity": "Uncommon",
      "image": "https://assets.tcgdex.net/es/swsh/swsh8/187",
      "types": [
        "Metálica"
      ],
      "illustrator": "Oswaldo KATO"
    },
    {
      "id": "swsh8-191",
      "name": "Cufant",
      "set": "swsh8",
      "setName": "Golpe Fusión",
      "number": "191",
      "rarity": "Común",
      "image": "https://assets.tcgdex.net/es/swsh/swsh8/191",
      "types": [
        "Metálica"
      ],
      "illustrator": "Oswaldo KATO"
    },
    {
      "id": "swsh8-206",
      "name": "Snorlax",
      "set": "swsh8",
      "setName": "Golpe Fusión",
      "number": "206",
      "rarity": "Común",
      "image": "https://assets.tcgdex.net/es/swsh/swsh8/206",
      "types": [
        "Incolora"
      ],
      "illustrator": "Oswaldo KATO"
    },
    {
      "id": "swsh8-242",
      "name": "Parque de Patinaje",
      "set": "swsh8",
      "setName": "Golpe Fusión",
      "number": "242",
      "rarity": "Uncommon",
      "image": "https://assets.tcgdex.net/es/swsh/swsh8/242",
      "types": null,
      "illustrator": "Oswaldo KATO"
    },
    {
      "id": "swsh8-41",
      "name": "Heatmor",
      "set": "swsh8",
      "setName": "Golpe Fusión",
      "number": "41",
      "rarity": "Uncommon",
      "image": "https://assets.tcgdex.net/es/swsh/swsh8/41",
      "types": [
        "Fuego"
      ],
      "illustrator": "Oswaldo KATO"
    },
    {
      "id": "swsh8-42",
      "name": "Oricorio",
      "set": "swsh8",
      "setName": "Golpe Fusión",
      "number": "42",
      "rarity": "Rara",
      "image": "https://assets.tcgdex.net/es/swsh/swsh8/42",
      "types": [
        "Fuego"
      ],
      "illustrator": "Oswaldo KATO"
    },
    {
      "id": "swshp-SWSH124",
      "name": "Zapdos de Galar",
      "set": "swshp",
      "setName": "Cartas de promoción ESES",
      "number": "SWSH124",
      "rarity": "Ninguno",
      "image": "https://assets.tcgdex.net/es/swsh/swshp/SWSH124",
      "types": [
        "Lucha"
      ],
      "illustrator": "Oswaldo KATO"
    }
  ]
}