{
  "name": "Alolan Persian GX",
  "totalCards": 3,
  "cards": [
    {
      "id": "sm12-129",
      "name": "Alolan Persian GX",
      "set": "sm12",
      "setName": "Cosmic Eclipse",
      "number": "129",
      "rarity": "Ultra Rare",
      "image": "https://assets.tcgdex.net/en/sm/sm12/129",
      "types": [
        "Darkness"
      ],
      "illustrator": "5ban Graphics"
    },
    {
      "id": "sm12-219",
      "name": "Alolan Persian GX",
      "set": "sm12",
      "setName": "Cosmic Eclipse",
      "number": "219",
      "rarity": "Ultra Rare",
      "image": "https://assets.tcgdex.net/en/sm/sm12/219",
      "types": [
        "Darkness"
      ],
      "illustrator": "PLANETA Tsuji"
    },
    {
      "id": "sm12-257",
      "name": "Alolan Persian GX",
      "set": "sm12",
      "setName": "Cosmic Eclipse",
      "number": "257",
      "rarity": "Secret Rare",
      "image": "https://assets.tcgdex.net/en/sm/sm12/257",
      "types": [
        "Darkness"
      ],
      "illustrator": "PLANETA Tsuji"
    }
  ]
}