{
  "name": "Loudred",
  "totalCards": 13,
  "cards": [
    {
      "id": "B1-191",
      "name": "Loudred",
      "set": "B1",
      "setName": "Mega Rising",
      "number": "191",
      "rarity": "One Diamond",
      "image": "https://assets.tcgdex.net/en/tcgp/B1/191",
      "types": [
        "Colorless"
      ],
      "illustrator": "MAHOU"
    },
    {
      "id": "bw8-106",
      "name": "Loudred",
      "set": "bw8",
      "setName": "Plasma Storm",
      "number": "106",
      "rarity": "Uncommon",
      "image": "https://assets.tcgdex.net/en/bw/bw8/106",
      "types": [
        "Colorless"
      ],
      "illustrator": "Aya Kusube"
    },
    {
      "id": "dp4-44",
      "name": "Loudred",
      "set": "dp4",
      "setName": "Great Encounters",
      "number": "44",
      "rarity": "Uncommon",
      "image": "https://assets.tcgdex.net/en/dp/dp4/44",
      "types": [
        "Colorless"
      ],
      "illustrator": "Ken Sugimori"
    },
    {
      "id": "ex14-23",
      "name": "Loudred",
      "set": "ex14",
      "setName": "Crystal Guardians",
      "number": "23",
      "rarity": "Rare",
      "image": "https://assets.tcgdex.net/en/ex/ex14/23",
      "types": [
        "Colorless"
      ],
      "illustrator": "Midori Harada"
    },
    {
      "id": "ex5-39",
      "name": "Loudred",
      "set": "ex5",
      "setName": "Hidden Legends",
      "number": "39",
      "rarity": "Uncommon",
      "image": "https://assets.tcgdex.net/en/ex/ex5/39",
      "types": [
        "Colorless"
      ],
      "illustrator": "Tomokazu Komiya"
    },
    {
      "id": "ex9-35",
      "name": "Loudred",
      "set": "ex9",
      "setName": "Emerald",
      "number": "35",
      "rarity": "Uncommon",
      "image": "https://assets.tcgdex.net/en/ex/ex9/35",
      "types": [
        "Colorless"
      ],
      "illustrator": "Hajime Kusajima"
    },
    {
      "id": "pl3-64",
      "name": "Loudred",
      "set": "pl3",
      "setName": "Supreme Victors",
      "number": "64",
      "rarity": "Uncommon",
      "image": "https://assets.tcgdex.net/en/pl/pl3/64",
      "types": [
        "Colorless"
      ],
      "illustrator": "Atsuko Nishida"
    },
    {
      "id": "sm7-118",
      "name": "Loudred",
      "set": "sm7",
      "setName": "Celestial Storm",
      "number": "118",
      "rarity": "Uncommon",
      "image": "https://assets.tcgdex.net/en/sm/sm7/118",
      "types": [
        "Colorless"
      ],
      "illustrator": "Masakazu Fukuda"
    },
    {
      "id": "sv04-149",
      "name": "Loudred",
      "set": "sv04",
      "setName": "Paradox Rift",
      "number": "149",
      "rarity": "Common",
      "image": "https://assets.tcgdex.net/en/sv/sv04/149",
      "types": [
        "Colorless"
      ],
      "illustrator": "Yukiko Baba"
    },
    {
      "id": "sv04-212",
      "name": "Loudred",
      "set": "sv04",
      "setName": "Paradox Rift",
      "number": "212",
      "rarity": "Illustration rare",
      "image": "https://assets.tcgdex.net/en/sv/sv04/212",
      "types": [
        "Colorless"
      ],
      "illustrator": "NC Empire"
    },
    {
      "id": "swsh4-136",
      "name": "Loudred",
      "set": "swsh4",
      "setName": "Vivid Voltage",
      "number": "136",
      "rarity": "Uncommon",
      "image": "https://assets.tcgdex.net/en/swsh/swsh4/136",
      "types": [
        "Colorless"
      ],
      "illustrator": "miki kudo"
    },
    {
      "id": "xy10-81",
      "name": "Loudred",
      "set": "xy10",
      "setName": "Fates Collide",
      "number": "81",
      "rarity": "Uncommon",
      "image": "https://assets.tcgdex.net/en/xy/xy10/81",
      "types": [
        "Colorless"
      ],
      "illustrator": "TOKIYA"
    },
    {
      "id": "xy4-84",
      "name": "Loudred",
      "set": "xy4",
      "setName": "Phantom Forces",
      "number": "84",
      "rarity": "Uncommon",
      "image": "https://assets.tcgdex.net/en/xy/xy4/84",
      "types": [
        "Colorless"
      ],
      "illustrator": "MAHOU"
    }
  ]
}